{
  "results": [
    {
      "code": "001200",
      "name": "유진투자증권",
      "market": "KOSPI",
      "close": 5980,
      "open": 5730,
      "high": 6260,
      "low": 5720,
      "volume": 6055540,
      "marketCap": 5793,
      "buyPrice": 5990,
      "target1": 6480,
      "target2": 6980,
      "stoploss": 5660,
      "rrRatio": 1.48,
      "atr": 345,
      "riskPct": 5.5,
      "momentum": 100,
      "conditionsMet": [
        "T1.200MA위",
        "T2.150MA위",
        "T3.50MA위",
        "T4.정배열",
        "T5.200MA상승",
        "T6.52주88%",
        "T7.저점+25%",
        "T8.거래량1.8x",
        "T9.양봉",
        "T10.전일↑",
        "T11.캔들양호",
        "T12.주가5천↑",
        "T13.거래대금362억",
        "T14.시총1천억↑",
        "B1.RSI최적64",
        "B2.MACD가속↑",
        "B3.52주권내88%",
        "B5.Stoch골든55",
        "B6.OBV매집",
        "B7.BB상단돌파93%",
        "B9.10MA돌파",
        "B10.RS강55%",
        "B11.거래증가1.8x",
        "S6.쌍끌이매수",
        "S7.외인13%",
        "S8.PER9.0",
        "S10.업종강세100%"
      ],
      "conditionsDetail": "23/25",
      "rsi": 63.5,
      "macdHist": 95.78,
      "volumeRatio": 2.1,
      "dataDate": "2026-05-04",
      "changeRate": 6.98,
      "foreignNet5d": 869045,
      "instNet5d": 350973,
      "foreignHold": 12.88,
      "foreignBuyDays": 3,
      "instBuyDays": 4,
      "per": 8.98,
      "pbr": 0.48,
      "eps": 666.0,
      "divYield": 3.01,
      "targetPrice": 0.0,
      "recommMean": 0.0,
      "sectorRatio": 100.0,
      "high52w": 6810.0,
      "low52w": 2665.0,
      "pos52w": 80.4,
      "distFromHigh": 12.2,
      "atrRatio": 0.96,
      "squeeze": false,
      "vwapDist": 2.4,
      "cmf": 0.112,
      "rocAccel": 14.56,
      "compression": 0.78,
      "insideDays": 2,
      "z20": 1.71,
      "z60": 2.15,
      "adx": 56.0,
      "rSquared": 0.74,
      "trendSlope": 67.9,
      "advancedTotal": 35,
      "f1_score": 5,
      "f2_score": 0,
      "f3_score": 6,
      "f4_score": 5,
      "f5_score": 6,
      "f6_score": 0,
      "f7_score": 6,
      "f8_score": 0,
      "f9_score": 1,
      "f10_score": 6,
      "rankScore": 78.1,
      "rank": 1
    },
    {
      "code": "003470",
      "name": "유안타증권",
      "market": "KOSPI",
      "close": 6030,
      "open": 5350,
      "high": 6440,
      "low": 5350,
      "volume": 22309182,
      "marketCap": 12036,
      "buyPrice": 6040,
      "target1": 6880,
      "target2": 7300,
      "stoploss": 5620,
      "rrRatio": 2.0,
      "atr": 276,
      "riskPct": 7.0,
      "momentum": 100,
      "conditionsMet": [
        "T1.200MA위",
        "T2.150MA위",
        "T3.50MA위",
        "T4.정배열",
        "T5.200MA상승",
        "T6.52주94%",
        "T7.저점+25%",
        "T8.거래량19.0x",
        "T9.양봉",
        "T10.전일↑",
        "T11.캔들양호",
        "T12.주가5천↑",
        "T13.거래대금1345억",
        "T14.시총1천억↑",
        "B1.RSI최적71",
        "B2.MACD가속↑",
        "B3.52주근접94%",
        "B5.Stoch골든74",
        "B6.OBV매집",
        "B7.BB상단돌파119%",
        "B8.양봉양호",
        "B9.10MA돌파",
        "B10.RS강46%",
        "B11.거래폭발19.0x",
        "S6.쌍끌이매수",
        "S7.외인66%",
        "S8.PER13.4",
        "S10.업종강세100%"
      ],
      "conditionsDetail": "24/25",
      "rsi": 70.9,
      "macdHist": 83.3,
      "volumeRatio": 22.0,
      "dataDate": "2026-05-04",
      "changeRate": 14.86,
      "foreignNet5d": 41957,
      "instNet5d": 1194,
      "foreignHold": 65.95,
      "foreignBuyDays": 2,
      "instBuyDays": 2,
      "per": 13.4,
      "pbr": 0.65,
      "eps": 450.0,
      "divYield": 3.65,
      "targetPrice": 0.0,
      "recommMean": 0.0,
      "sectorRatio": 100.0,
      "high52w": 6440.0,
      "low52w": 2775.0,
      "pos52w": 88.8,
      "distFromHigh": 6.4,
      "atrRatio": 0.93,
      "squeeze": false,
      "vwapDist": 6.3,
      "cmf": 0.182,
      "rocAccel": 14.4,
      "compression": 0.77,
      "insideDays": 1,
      "z20": 2.74,
      "z60": 2.96,
      "adx": 72.8,
      "rSquared": 0.8,
      "trendSlope": 53.2,
      "advancedTotal": 22,
      "f1_score": -2,
      "f2_score": 0,
      "f3_score": 2,
      "f4_score": 7,
      "f5_score": 6,
      "f6_score": 0,
      "f7_score": 6,
      "f8_score": 0,
      "f9_score": -3,
      "f10_score": 6,
      "rankScore": 77.0,
      "rank": 2
    },
    {
      "code": "030610",
      "name": "교보증권",
      "market": "KOSPI",
      "close": 14710,
      "open": 13920,
      "high": 15330,
      "low": 13860,
      "volume": 714884,
      "marketCap": 16764,
      "buyPrice": 14750,
      "target1": 16050,
      "target2": 17360,
      "stoploss": 13880,
      "rrRatio": 1.49,
      "atr": 575,
      "riskPct": 5.9,
      "momentum": 100,
      "conditionsMet": [
        "T1.200MA위",
        "T2.150MA위",
        "T3.50MA위",
        "T4.정배열",
        "T5.200MA상승",
        "T6.52주81%",
        "T7.저점+25%",
        "T8.거래량3.8x",
        "T9.양봉",
        "T10.전일↑",
        "T11.캔들양호",
        "T12.주가5천↑",
        "T13.거래대금105억",
        "T14.시총1천억↑",
        "B1.RSI최적66",
        "B2.MACD가속↑",
        "B5.Stoch골든75",
        "B6.OBV매집",
        "B7.BB상단돌파93%",
        "B8.양봉양호",
        "B9.10MA돌파",
        "B10.RS강28%",
        "B11.거래폭발3.8x",
        "S6.쌍끌이매수",
        "S8.PER11.7",
        "S10.업종강세100%"
      ],
      "conditionsDetail": "23/25",
      "rsi": 65.8,
      "macdHist": 99.55,
      "volumeRatio": 4.2,
      "dataDate": "2026-05-04",
      "changeRate": 7.92,
      "foreignNet5d": 116158,
      "instNet5d": 40852,
      "foreignHold": 1.22,
      "foreignBuyDays": 4,
      "instBuyDays": 4,
      "per": 11.73,
      "pbr": 0.78,
      "eps": 1254.0,
      "divYield": 3.74,
      "targetPrice": 0.0,
      "recommMean": 0.0,
      "sectorRatio": 100.0,
      "high52w": 18820.0,
      "low52w": 6440.0,
      "pos52w": 70.6,
      "distFromHigh": 19.3,
      "atrRatio": 0.76,
      "squeeze": false,
      "vwapDist": 7.7,
      "cmf": -0.017,
      "rocAccel": 4.4,
      "compression": 0.66,
      "insideDays": 2,
      "z20": 1.73,
      "z60": 1.39,
      "adx": 45.7,
      "rSquared": 0.85,
      "trendSlope": 125.0,
      "advancedTotal": 30,
      "f1_score": 5,
      "f2_score": 4,
      "f3_score": 2,
      "f4_score": 0,
      "f5_score": 6,
      "f6_score": 0,
      "f7_score": 6,
      "f8_score": 0,
      "f9_score": 1,
      "f10_score": 6,
      "rankScore": 76.2,
      "rank": 3
    },
    {
      "code": "016360",
      "name": "삼성증권",
      "market": "KOSPI",
      "close": 137900,
      "open": 110400,
      "high": 139700,
      "low": 109600,
      "volume": 4185136,
      "marketCap": 123145,
      "buyPrice": 138300,
      "target1": 154300,
      "target2": 162300,
      "stoploss": 130300,
      "rrRatio": 2.0,
      "atr": 5314,
      "riskPct": 5.8,
      "momentum": 100,
      "conditionsMet": [
        "T1.200MA위",
        "T2.150MA위",
        "T3.50MA위",
        "T4.정배열",
        "T5.200MA상승",
        "T6.52주99%",
        "T7.저점+25%",
        "T8.거래량8.5x",
        "T9.양봉",
        "T10.전일↑",
        "T11.캔들양호",
        "T12.주가5천↑",
        "T13.거래대금5771억",
        "T14.시총1천억↑",
        "B2.MACD가속↑",
        "B3.52주신고가99%",
        "B5.Stoch상승94",
        "B6.OBV매집",
        "B7.BB상단돌파136%",
        "B8.장대양봉",
        "B9.10MA돌파",
        "B10.RS강56%",
        "B11.거래폭발8.5x",
        "S6.쌍끌이매수",
        "S7.외인28%",
        "S8.PER12.2",
        "S10.업종강세100%"
      ],
      "conditionsDetail": "23/25",
      "rsi": 77.7,
      "macdHist": 1396.38,
      "volumeRatio": 8.8,
      "dataDate": "2026-05-04",
      "changeRate": 28.28,
      "foreignNet5d": 160794,
      "instNet5d": 69241,
      "foreignHold": 27.79,
      "foreignBuyDays": 3,
      "instBuyDays": 1,
      "per": 12.23,
      "pbr": 1.53,
      "eps": 11279.0,
      "divYield": 2.9,
      "targetPrice": 132889.0,
      "recommMean": 4.0,
      "sectorRatio": 100.0,
      "high52w": 139700.0,
      "low52w": 52400.0,
      "pos52w": 98.1,
      "distFromHigh": 1.3,
      "atrRatio": 0.93,
      "squeeze": false,
      "vwapDist": 18.5,
      "cmf": 0.254,
      "rocAccel": 20.87,
      "compression": 0.7,
      "insideDays": 2,
      "z20": 3.45,
      "z60": 4.05,
      "adx": 72.9,
      "rSquared": 0.47,
      "trendSlope": 963.6,
      "advancedTotal": 17,
      "f1_score": -5,
      "f2_score": 0,
      "f3_score": 0,
      "f4_score": 7,
      "f5_score": 6,
      "f6_score": 0,
      "f7_score": 6,
      "f8_score": 0,
      "f9_score": -3,
      "f10_score": 6,
      "rankScore": 73.0,
      "rank": 4
    },
    {
      "code": "039440",
      "name": "에스티아이",
      "market": "KOSDAQ",
      "close": 40850,
      "open": 38500,
      "high": 41900,
      "low": 38400,
      "volume": 806896,
      "marketCap": 6335,
      "buyPrice": 40950,
      "target1": 45300,
      "target2": 49650,
      "stoploss": 38050,
      "rrRatio": 1.5,
      "atr": 2007,
      "riskPct": 7.1,
      "momentum": 100,
      "conditionsMet": [
        "T1.200MA위",
        "T2.150MA위",
        "T3.50MA위",
        "T4.정배열",
        "T5.200MA상승",
        "T6.52주95%",
        "T7.저점+25%",
        "T8.거래량2.7x",
        "T9.양봉",
        "T10.전일↑",
        "T11.캔들양호",
        "T12.주가5천↑",
        "T13.거래대금330억",
        "T14.시총1천억↑",
        "B1.RSI최적69",
        "B2.MACD가속↑",
        "B3.52주근접95%",
        "B5.Stoch상승90",
        "B6.OBV매집",
        "B7.BB상단돌파96%",
        "B8.양봉양호",
        "B9.10MA돌파",
        "B10.RS강22%",
        "B11.거래급증2.7x",
        "S6.쌍끌이매수",
        "S9.목표+20%",
        "S10.업종강세100%"
      ],
      "conditionsDetail": "24/25",
      "rsi": 68.8,
      "macdHist": 701.3,
      "volumeRatio": 2.7,
      "dataDate": "2026-05-04",
      "changeRate": 9.22,
      "foreignNet5d": 42033,
      "instNet5d": 109760,
      "foreignHold": 4.4,
      "foreignBuyDays": 2,
      "instBuyDays": 3,
      "per": 41.94,
      "pbr": 2.18,
      "eps": 974.0,
      "divYield": 0.37,
      "targetPrice": 49000.0,
      "recommMean": 4.0,
      "sectorRatio": 100.0,
      "high52w": 43200.0,
      "low52w": 17380.0,
      "pos52w": 90.9,
      "distFromHigh": 5.4,
      "atrRatio": 0.85,
      "squeeze": false,
      "vwapDist": 14.6,
      "cmf": 0.158,
      "rocAccel": -1.11,
      "compression": 0.67,
      "insideDays": 0,
      "z20": 1.85,
      "z60": 2.35,
      "adx": 74.5,
      "rSquared": 0.94,
      "trendSlope": 580.3,
      "advancedTotal": 23,
      "f1_score": -2,
      "f2_score": 4,
      "f3_score": 0,
      "f4_score": 7,
      "f5_score": 1,
      "f6_score": 0,
      "f7_score": 6,
      "f8_score": 0,
      "f9_score": 1,
      "f10_score": 6,
      "rankScore": 72.6,
      "rank": 5
    },
    {
      "code": "432720",
      "name": "퀄리타스반도체",
      "market": "KOSDAQ",
      "close": 29500,
      "open": 26050,
      "high": 31350,
      "low": 26050,
      "volume": 7001910,
      "marketCap": 4176,
      "buyPrice": 29550,
      "target1": 33750,
      "target2": 35850,
      "stoploss": 27450,
      "rrRatio": 2.0,
      "atr": 2664,
      "riskPct": 7.1,
      "momentum": 100,
      "conditionsMet": [
        "T1.200MA위",
        "T2.150MA위",
        "T3.50MA위",
        "T4.정배열",
        "T5.200MA상승",
        "T6.52주94%",
        "T7.저점+25%",
        "T8.거래량4.8x",
        "T9.양봉",
        "T10.전일↑",
        "T11.캔들양호",
        "T12.주가5천↑",
        "T13.거래대금2066억",
        "T14.시총1천억↑",
        "B2.MACD가속↑",
        "B3.52주근접94%",
        "B5.Stoch상승88",
        "B6.OBV매집",
        "B7.BB상단돌파120%",
        "B8.양봉양호",
        "B9.10MA돌파",
        "B10.RS강99%",
        "B11.거래폭발4.8x",
        "S6.쌍끌이매수",
        "S10.업종강세100%"
      ],
      "conditionsDetail": "23/25",
      "rsi": 79.9,
      "macdHist": 796.37,
      "volumeRatio": 4.7,
      "dataDate": "2026-05-04",
      "changeRate": 17.76,
      "foreignNet5d": 183258,
      "instNet5d": 11572,
      "foreignHold": 3.73,
      "foreignBuyDays": 4,
      "instBuyDays": 2,
      "per": 0.0,
      "pbr": 11.49,
      "eps": -1643.0,
      "divYield": 0.0,
      "targetPrice": 0.0,
      "recommMean": 0.0,
      "sectorRatio": 100.0,
      "high52w": 31350.0,
      "low52w": 10190.0,
      "pos52w": 91.3,
      "distFromHigh": 5.9,
      "atrRatio": 1.64,
      "squeeze": false,
      "vwapDist": 37.1,
      "cmf": 0.19,
      "rocAccel": 21.64,
      "compression": 0.76,
      "insideDays": 1,
      "z20": 2.79,
      "z60": 3.91,
      "adx": 74.7,
      "rSquared": 0.73,
      "trendSlope": 525.1,
      "advancedTotal": 20,
      "f1_score": -2,
      "f2_score": 0,
      "f3_score": 0,
      "f4_score": 7,
      "f5_score": 6,
      "f6_score": 0,
      "f7_score": 6,
      "f8_score": 0,
      "f9_score": -3,
      "f10_score": 6,
      "rankScore": 72.5,
      "rank": 6
    },
    {
      "code": "010170",
      "name": "대한광통신",
      "market": "KOSDAQ",
      "close": 17700,
      "open": 15490,
      "high": 18200,
      "low": 15490,
      "volume": 82980381,
      "marketCap": 27521,
      "buyPrice": 17750,
      "target1": 20120,
      "target2": 21500,
      "stoploss": 16500,
      "rrRatio": 1.9,
      "atr": 2274,
      "riskPct": 7.0,
      "momentum": 100,
      "conditionsMet": [
        "T1.200MA위",
        "T2.150MA위",
        "T3.50MA위",
        "T4.정배열",
        "T5.200MA상승",
        "T6.52주80%",
        "T7.저점+25%",
        "T8.거래량2.2x",
        "T9.양봉",
        "T10.전일↑",
        "T11.캔들양호",
        "T12.주가5천↑",
        "T13.거래대금14688억",
        "T14.시총1천억↑",
        "B1.RSI최적63",
        "B2.MACD반전",
        "B4.VCP수축(0.8ATR)",
        "B5.Stoch골든51",
        "B6.OBV매집",
        "B7.BB상단72%",
        "B8.장대양봉",
        "B10.RS강432%",
        "B11.거래급증2.2x",
        "S6.쌍끌이매수",
        "S10.업종강세83%"
      ],
      "conditionsDetail": "23/25",
      "rsi": 63.3,
      "macdHist": -298.31,
      "volumeRatio": 2.2,
      "dataDate": "2026-05-04",
      "changeRate": 16.83,
      "foreignNet5d": 1177168,
      "instNet5d": 981394,
      "foreignHold": 5.24,
      "foreignBuyDays": 2,
      "instBuyDays": 3,
      "per": 0.0,
      "pbr": 36.05,
      "eps": -242.0,
      "divYield": 0.0,
      "targetPrice": 0.0,
      "recommMean": 0.0,
      "sectorRatio": 83.33333333333334,
      "high52w": 22000.0,
      "low52w": 551.0,
      "pos52w": 80.0,
      "distFromHigh": 19.5,
      "atrRatio": 1.64,
      "squeeze": false,
      "vwapDist": 10.5,
      "cmf": 0.051,
      "rocAccel": 38.42,
      "compression": 0.51,
      "insideDays": 1,
      "z20": 0.88,
      "z60": 1.62,
      "adx": 15.9,
      "rSquared": 0.0,
      "trendSlope": -1.2,
      "advancedTotal": 30,
      "f1_score": 5,
      "f2_score": 0,
      "f3_score": 0,
      "f4_score": 5,
      "f5_score": 6,
      "f6_score": 4,
      "f7_score": 6,
      "f8_score": 0,
      "f9_score": 4,
      "f10_score": 0,
      "rankScore": 71.7,
      "rank": 7
    },
    {
      "code": "036890",
      "name": "진성티이씨",
      "market": "KOSDAQ",
      "close": 19290,
      "open": 18460,
      "high": 19630,
      "low": 18390,
      "volume": 551570,
      "marketCap": 4250,
      "buyPrice": 19340,
      "target1": 21540,
      "target2": 22640,
      "stoploss": 18240,
      "rrRatio": 2.0,
      "atr": 730,
      "riskPct": 5.7,
      "momentum": 100,
      "conditionsMet": [
        "T1.200MA위",
        "T2.150MA위",
        "T3.50MA위",
        "T4.정배열",
        "T5.200MA상승",
        "T6.52주98%",
        "T7.저점+25%",
        "T8.거래량2.2x",
        "T9.양봉",
        "T10.전일↑",
        "T11.캔들양호",
        "T12.주가5천↑",
        "T13.거래대금106억",
        "T14.시총1천억↑",
        "B1.RSI최적66",
        "B2.MACD가속↑",
        "B3.52주신고가98%",
        "B5.Stoch상승87",
        "B6.OBV매집",
        "B7.BB상단돌파109%",
        "B8.양봉양호",
        "B9.10MA돌파",
        "B10.RS강41%",
        "B11.거래급증2.2x",
        "S6.쌍끌이매수",
        "S7.외인12%",
        "S8.PER13.2",
        "S10.업종보통"
      ],
      "conditionsDetail": "24/25",
      "rsi": 66.4,
      "macdHist": 83.51,
      "volumeRatio": 2.2,
      "dataDate": "2026-05-04",
      "changeRate": 8.37,
      "foreignNet5d": 171046,
      "instNet5d": 76297,
      "foreignHold": 11.73,
      "foreignBuyDays": 4,
      "instBuyDays": 3,
      "per": 13.2,
      "pbr": 1.3,
      "eps": 1461.0,
      "divYield": 1.71,
      "targetPrice": 0.0,
      "recommMean": 0.0,
      "sectorRatio": 66.66666666666666,
      "high52w": 19630.0,
      "low52w": 9000.0,
      "pos52w": 96.9,
      "distFromHigh": 1.7,
      "atrRatio": 0.72,
      "squeeze": true,
      "vwapDist": 8.8,
      "cmf": 0.014,
      "rocAccel": 7.4,
      "compression": 0.64,
      "insideDays": 0,
      "z20": 2.37,
      "z60": 2.4,
      "adx": 54.2,
      "rSquared": 0.57,
      "trendSlope": 94.5,
      "advancedTotal": 20,
      "f1_score": -5,
      "f2_score": 8,
      "f3_score": 0,
      "f4_score": 2,
      "f5_score": 6,
      "f6_score": 0,
      "f7_score": 6,
      "f8_score": 0,
      "f9_score": -3,
      "f10_score": 6,
      "rankScore": 71.7,
      "rank": 8
    },
    {
      "code": "020150",
      "name": "롯데에너지머티리얼즈",
      "market": "KOSPI",
      "close": 78500,
      "open": 70800,
      "high": 83100,
      "low": 70800,
      "volume": 1230570,
      "marketCap": 41107,
      "buyPrice": 78700,
      "target1": 89900,
      "target2": 95500,
      "stoploss": 73100,
      "rrRatio": 2.0,
      "atr": 5471,
      "riskPct": 7.1,
      "momentum": 100,
      "conditionsMet": [
        "T1.200MA위",
        "T2.150MA위",
        "T3.50MA위",
        "T4.정배열",
        "T5.200MA상승",
        "T6.52주94%",
        "T7.저점+25%",
        "T8.거래량3.4x",
        "T9.양봉",
        "T10.전일↑",
        "T11.캔들양호",
        "T12.주가5천↑",
        "T13.거래대금966억",
        "T14.시총1천억↑",
        "B2.MACD가속↑",
        "B3.52주근접94%",
        "B5.Stoch상승88",
        "B6.OBV매집",
        "B7.BB상단돌파103%",
        "B8.양봉양호",
        "B9.10MA돌파",
        "B10.RS강83%",
        "B11.거래폭발3.4x",
        "S6.쌍끌이매수",
        "S10.업종보통"
      ],
      "conditionsDetail": "23/25",
      "rsi": 83.2,
      "macdHist": 1884.13,
      "volumeRatio": 3.4,
      "dataDate": "2026-05-04",
      "changeRate": 17.69,
      "foreignNet5d": 13033,
      "instNet5d": 222199,
      "foreignHold": 8.72,
      "foreignBuyDays": 2,
      "instBuyDays": 5,
      "per": 0.0,
      "pbr": 2.48,
      "eps": -3065.0,
      "divYield": 0.0,
      "targetPrice": 60100.0,
      "recommMean": 3.9,
      "sectorRatio": 66.66666666666666,
      "high52w": 83100.0,
      "low52w": 15550.0,
      "pos52w": 92.8,
      "distFromHigh": 5.5,
      "atrRatio": 1.43,
      "squeeze": false,
      "vwapDist": 36.1,
      "cmf": 0.242,
      "rocAccel": 9.84,
      "compression": 0.77,
      "insideDays": 1,
      "z20": 2.12,
      "z60": 3.34,
      "adx": 90.2,
      "rSquared": 0.89,
      "trendSlope": 1685.3,
      "advancedTotal": 20,
      "f1_score": -2,
      "f2_score": 0,
      "f3_score": 0,
      "f4_score": 7,
      "f5_score": 6,
      "f6_score": 0,
      "f7_score": 6,
      "f8_score": 0,
      "f9_score": -3,
      "f10_score": 6,
      "rankScore": 71.5,
      "rank": 9
    },
    {
      "code": "006800",
      "name": "미래에셋증권",
      "market": "KOSPI",
      "close": 70300,
      "open": 66500,
      "high": 71700,
      "low": 65900,
      "volume": 6411137,
      "marketCap": 393376,
      "buyPrice": 70500,
      "target1": 78000,
      "target2": 85500,
      "stoploss": 65500,
      "rrRatio": 1.5,
      "atr": 3636,
      "riskPct": 7.1,
      "momentum": 100,
      "conditionsMet": [
        "T1.200MA위",
        "T2.150MA위",
        "T3.50MA위",
        "T4.정배열",
        "T5.200MA상승",
        "T6.52주91%",
        "T7.저점+25%",
        "T8.거래량1.6x",
        "T9.양봉",
        "T10.전일↑",
        "T11.캔들양호",
        "T12.주가5천↑",
        "T13.거래대금4507억",
        "T14.시총1천억↑",
        "B1.RSI최적56",
        "B2.MACD반전",
        "B3.52주권내91%",
        "B5.Stoch골든60",
        "B6.OBV매집",
        "B7.BB상단73%",
        "B8.양봉양호",
        "B9.10MA돌파",
        "B10.RS강103%",
        "B11.거래증가1.6x",
        "S6.쌍끌이매수",
        "S10.업종강세100%"
      ],
      "conditionsDetail": "24/25",
      "rsi": 55.9,
      "macdHist": -297.51,
      "volumeRatio": 1.6,
      "dataDate": "2026-05-04",
      "changeRate": 8.49,
      "foreignNet5d": 1344842,
      "instNet5d": 531185,
      "foreignHold": 9.35,
      "foreignBuyDays": 3,
      "instBuyDays": 2,
      "per": 32.64,
      "pbr": 3.1,
      "eps": 2154.0,
      "divYield": 0.42,
      "targetPrice": 69397.0,
      "recommMean": 3.29,
      "sectorRatio": 100.0,
      "high52w": 76966.0,
      "low52w": 11749.0,
      "pos52w": 90.0,
      "distFromHigh": 8.7,
      "atrRatio": 0.74,
      "squeeze": true,
      "vwapDist": 2.3,
      "cmf": -0.073,
      "rocAccel": -0.74,
      "compression": 0.54,
      "insideDays": 1,
      "z20": 0.92,
      "z60": 0.83,
      "adx": 30.9,
      "rSquared": 0.11,
      "trendSlope": 146.8,
      "advancedTotal": 27,
      "f1_score": -2,
      "f2_score": 8,
      "f3_score": 6,
      "f4_score": 0,
      "f5_score": 1,
      "f6_score": 4,
      "f7_score": 6,
      "f8_score": 0,
      "f9_score": 4,
      "f10_score": 0,
      "rankScore": 71.2,
      "rank": 10
    },
    {
      "code": "001740",
      "name": "SK네트웍스",
      "market": "KOSPI",
      "close": 6590,
      "open": 5990,
      "high": 6800,
      "low": 5870,
      "volume": 11611864,
      "marketCap": 14582,
      "buyPrice": 6600,
      "target1": 7380,
      "target2": 7770,
      "stoploss": 6210,
      "rrRatio": 2.0,
      "atr": 257,
      "riskPct": 5.9,
      "momentum": 100,
      "conditionsMet": [
        "T1.200MA위",
        "T2.150MA위",
        "T3.50MA위",
        "T4.정배열",
        "T5.200MA상승",
        "T6.52주97%",
        "T7.저점+25%",
        "T8.거래량7.9x",
        "T9.양봉",
        "T10.전일↑",
        "T11.캔들양호",
        "T12.주가5천↑",
        "T13.거래대금765억",
        "T14.시총1천억↑",
        "B1.RSI최적72",
        "B2.MACD가속↑",
        "B3.52주근접97%",
        "B5.Stoch상승86",
        "B6.OBV매집",
        "B7.BB상단돌파126%",
        "B8.양봉양호",
        "B9.10MA돌파",
        "B10.RS강38%",
        "B11.거래폭발7.9x",
        "S6.기관매수5일",
        "S7.외인15%",
        "S10.업종강세83%"
      ],
      "conditionsDetail": "24/25",
      "rsi": 72.3,
      "macdHist": 98.1,
      "volumeRatio": 7.9,
      "dataDate": "2026-05-04",
      "changeRate": 12.27,
      "foreignNet5d": -911214,
      "instNet5d": 467298,
      "foreignHold": 14.76,
      "foreignBuyDays": 0,
      "instBuyDays": 5,
      "per": 29.29,
      "pbr": 0.63,
      "eps": 225.0,
      "divYield": 3.79,
      "targetPrice": 7040.0,
      "recommMean": 4.0,
      "sectorRatio": 83.33333333333334,
      "high52w": 6800.0,
      "low52w": 3915.0,
      "pos52w": 92.7,
      "distFromHigh": 3.1,
      "atrRatio": 0.83,
      "squeeze": false,
      "vwapDist": 12.7,
      "cmf": 0.244,
      "rocAccel": 15.39,
      "compression": 0.86,
      "insideDays": 2,
      "z20": 3.04,
      "z60": 4.03,
      "adx": 85.3,
      "rSquared": 0.69,
      "trendSlope": 48.8,
      "advancedTotal": 18,
      "f1_score": -2,
      "f2_score": 4,
      "f3_score": 0,
      "f4_score": 7,
      "f5_score": 6,
      "f6_score": 0,
      "f7_score": 0,
      "f8_score": 0,
      "f9_score": -3,
      "f10_score": 6,
      "rankScore": 69.0,
      "rank": 11
    },
    {
      "code": "005690",
      "name": "파미셀",
      "market": "KOSPI",
      "close": 20250,
      "open": 18700,
      "high": 21150,
      "low": 18650,
      "volume": 3583774,
      "marketCap": 12153,
      "buyPrice": 20300,
      "target1": 22450,
      "target2": 24650,
      "stoploss": 18850,
      "rrRatio": 1.48,
      "atr": 1294,
      "riskPct": 7.1,
      "momentum": 100,
      "conditionsMet": [
        "T1.200MA위",
        "T2.150MA위",
        "T3.50MA위",
        "T4.정배열",
        "T5.200MA상승",
        "T6.52주96%",
        "T7.저점+25%",
        "T8.거래량2.8x",
        "T9.양봉",
        "T10.전일↑",
        "T11.캔들양호",
        "T12.주가5천↑",
        "T13.거래대금726억",
        "T14.시총1천억↑",
        "B1.RSI최적62",
        "B2.MACD가속↑",
        "B3.52주근접96%",
        "B5.Stoch골든78",
        "B6.OBV매집",
        "B7.BB상단88%",
        "B8.양봉양호",
        "B9.10MA돌파",
        "B10.RS강42%",
        "B11.거래급증2.8x",
        "S6.쌍끌이매수",
        "S7.외인12%",
        "S9.목표+21%",
        "S10.업종보통"
      ],
      "conditionsDetail": "24/25",
      "rsi": 62.1,
      "macdHist": 118.5,
      "volumeRatio": 2.9,
      "dataDate": "2026-05-04",
      "changeRate": 11.82,
      "foreignNet5d": 361767,
      "instNet5d": 209606,
      "foreignHold": 11.61,
      "foreignBuyDays": 3,
      "instBuyDays": 4,
      "per": 30.18,
      "pbr": 9.81,
      "eps": 671.0,
      "divYield": 0.25,
      "targetPrice": 24500.0,
      "recommMean": 4.0,
      "sectorRatio": 66.66666666666666,
      "high52w": 21200.0,
      "low52w": 10360.0,
      "pos52w": 92.1,
      "distFromHigh": 4.3,
      "atrRatio": 1.09,
      "squeeze": false,
      "vwapDist": 9.5,
      "cmf": 0.166,
      "rocAccel": -0.85,
      "compression": 0.6,
      "insideDays": 1,
      "z20": 1.52,
      "z60": 2.17,
      "adx": 33.5,
      "rSquared": 0.68,
      "trendSlope": 215.3,
      "advancedTotal": 19,
      "f1_score": -2,
      "f2_score": 0,
      "f3_score": 0,
      "f4_score": 7,
      "f5_score": 1,
      "f6_score": 0,
      "f7_score": 6,
      "f8_score": 0,
      "f9_score": 1,
      "f10_score": 6,
      "rankScore": 68.6,
      "rank": 12
    },
    {
      "code": "006340",
      "name": "대원전선",
      "market": "KOSPI",
      "close": 17350,
      "open": 16380,
      "high": 18560,
      "low": 15850,
      "volume": 40809540,
      "marketCap": 13605,
      "buyPrice": 17400,
      "target1": 19840,
      "target2": 21060,
      "stoploss": 16180,
      "rrRatio": 2.0,
      "atr": 1509,
      "riskPct": 7.0,
      "momentum": 100,
      "conditionsMet": [
        "T1.200MA위",
        "T2.150MA위",
        "T3.50MA위",
        "T4.정배열",
        "T5.200MA상승",
        "T6.52주93%",
        "T7.저점+25%",
        "T8.거래량1.8x",
        "T9.양봉",
        "T10.전일↑",
        "T11.캔들양호",
        "T12.주가5천↑",
        "T13.거래대금7080억",
        "T14.시총1천억↑",
        "B2.MACD가속↑",
        "B3.52주근접93%",
        "B6.OBV매집",
        "B7.BB상단돌파117%",
        "B9.10MA돌파",
        "B10.RS강356%",
        "B11.거래증가1.8x",
        "S6.쌍끌이매수",
        "S10.업종강세100%"
      ],
      "conditionsDetail": "21/25",
      "rsi": 91.6,
      "macdHist": 1078.02,
      "volumeRatio": 1.8,
      "dataDate": "2026-05-04",
      "changeRate": 15.28,
      "foreignNet5d": 60783,
      "instNet5d": 555302,
      "foreignHold": 4.41,
      "foreignBuyDays": 2,
      "instBuyDays": 4,
      "per": 153.54,
      "pbr": 11.36,
      "eps": 113.0,
      "divYield": 0.0,
      "targetPrice": 0.0,
      "recommMean": 0.0,
      "sectorRatio": 100.0,
      "high52w": 18560.0,
      "low52w": 2730.0,
      "pos52w": 92.4,
      "distFromHigh": 6.5,
      "atrRatio": 1.94,
      "squeeze": false,
      "vwapDist": 73.6,
      "cmf": 0.369,
      "rocAccel": 115.39,
      "compression": 0.91,
      "insideDays": 1,
      "z20": 2.66,
      "z60": 4.45,
      "adx": 95.0,
      "rSquared": 0.73,
      "trendSlope": 508.5,
      "advancedTotal": 20,
      "f1_score": -2,
      "f2_score": 0,
      "f3_score": 0,
      "f4_score": 7,
      "f5_score": 6,
      "f6_score": 0,
      "f7_score": 6,
      "f8_score": 0,
      "f9_score": -3,
      "f10_score": 6,
      "rankScore": 68.6,
      "rank": 13
    },
    {
      "code": "251370",
      "name": "와이엠티",
      "market": "KOSDAQ",
      "close": 20650,
      "open": 18260,
      "high": 21000,
      "low": 17810,
      "volume": 1367493,
      "marketCap": 3776,
      "buyPrice": 20700,
      "target1": 23600,
      "target2": 25050,
      "stoploss": 19250,
      "rrRatio": 2.0,
      "atr": 1186,
      "riskPct": 7.0,
      "momentum": 100,
      "conditionsMet": [
        "T1.200MA위",
        "T2.150MA위",
        "T3.50MA위",
        "T4.정배열",
        "T5.200MA상승",
        "T6.52주98%",
        "T7.저점+25%",
        "T8.거래량4.1x",
        "T9.양봉",
        "T10.전일↑",
        "T11.캔들양호",
        "T12.주가5천↑",
        "T13.거래대금282억",
        "T14.시총1천억↑",
        "B1.RSI최적72",
        "B2.MACD가속↑",
        "B3.52주신고가98%",
        "B5.Stoch상승93",
        "B6.OBV매집",
        "B7.BB상단돌파123%",
        "B8.장대양봉",
        "B9.10MA돌파",
        "B10.RS강80%",
        "B11.거래폭발4.1x",
        "S6.쌍끌이매수",
        "S10.업종보통"
      ],
      "conditionsDetail": "24/25",
      "rsi": 71.7,
      "macdHist": 119.64,
      "volumeRatio": 4.1,
      "dataDate": "2026-05-04",
      "changeRate": 15.3,
      "foreignNet5d": 291804,
      "instNet5d": 327905,
      "foreignHold": 6.56,
      "foreignBuyDays": 2,
      "instBuyDays": 3,
      "per": 0.0,
      "pbr": 1.89,
      "eps": -101.0,
      "divYield": 0.0,
      "targetPrice": 0.0,
      "recommMean": 0.0,
      "sectorRatio": 66.66666666666666,
      "high52w": 21000.0,
      "low52w": 8710.0,
      "pos52w": 97.2,
      "distFromHigh": 1.7,
      "atrRatio": 1.03,
      "squeeze": false,
      "vwapDist": 17.8,
      "cmf": 0.115,
      "rocAccel": 14.41,
      "compression": 0.67,
      "insideDays": 1,
      "z20": 2.92,
      "z60": 2.82,
      "adx": 52.8,
      "rSquared": 0.47,
      "trendSlope": 139.1,
      "advancedTotal": 9,
      "f1_score": -5,
      "f2_score": 0,
      "f3_score": 0,
      "f4_score": 5,
      "f5_score": 6,
      "f6_score": 0,
      "f7_score": 0,
      "f8_score": 0,
      "f9_score": -3,
      "f10_score": 6,
      "rankScore": 68.4,
      "rank": 14
    },
    {
      "code": "005490",
      "name": "POSCO홀딩스",
      "market": "KOSPI",
      "close": 502000,
      "open": 486000,
      "high": 512000,
      "low": 485000,
      "volume": 1080353,
      "marketCap": 397792,
      "buyPrice": 503000,
      "target1": 549000,
      "target2": 572000,
      "stoploss": 480000,
      "rrRatio": 2.0,
      "atr": 20071,
      "riskPct": 4.6,
      "momentum": 100,
      "conditionsMet": [
        "T1.200MA위",
        "T2.150MA위",
        "T3.50MA위",
        "T4.정배열",
        "T5.200MA상승",
        "T6.52주98%",
        "T7.저점+25%",
        "T8.거래량2.3x",
        "T9.양봉",
        "T10.전일↑",
        "T11.캔들양호",
        "T12.주가5천↑",
        "T13.거래대금5423억",
        "T14.시총1천억↑",
        "B2.MACD가속↑",
        "B3.52주신고가98%",
        "B5.Stoch상승93",
        "B6.OBV매집",
        "B7.BB상단돌파106%",
        "B8.양봉양호",
        "B9.10MA돌파",
        "B10.RS강33%",
        "B11.거래급증2.3x",
        "S6.쌍끌이매수",
        "S7.외인31%"
      ],
      "conditionsDetail": "23/25",
      "rsi": 81.7,
      "macdHist": 10557.82,
      "volumeRatio": 2.3,
      "dataDate": "2026-05-04",
      "changeRate": 8.66,
      "foreignNet5d": 424602,
      "instNet5d": 376341,
      "foreignHold": 31.07,
      "foreignBuyDays": 2,
      "instBuyDays": 5,
      "per": 62.09,
      "pbr": 0.68,
      "eps": 8085.0,
      "divYield": 1.99,
      "targetPrice": 498286.0,
      "recommMean": 4.0,
      "sectorRatio": 33.33333333333333,
      "high52w": 512000.0,
      "low52w": 230000.0,
      "pos52w": 96.5,
      "distFromHigh": 2.0,
      "atrRatio": 1.16,
      "squeeze": false,
      "vwapDist": 19.1,
      "cmf": 0.224,
      "rocAccel": 17.92,
      "compression": 0.75,
      "insideDays": 2,
      "z20": 2.23,
      "z60": 3.41,
      "adx": 82.2,
      "rSquared": 0.88,
      "trendSlope": 7189.1,
      "advancedTotal": 17,
      "f1_score": -5,
      "f2_score": 0,
      "f3_score": 0,
      "f4_score": 7,
      "f5_score": 6,
      "f6_score": 0,
      "f7_score": 6,
      "f8_score": 0,
      "f9_score": -3,
      "f10_score": 6,
      "rankScore": 68.0,
      "rank": 15
    },
    {
      "code": "219130",
      "name": "타이거일렉",
      "market": "KOSDAQ",
      "close": 52600,
      "open": 46300,
      "high": 53700,
      "low": 46200,
      "volume": 156770,
      "marketCap": 3321,
      "buyPrice": 52700,
      "target1": 60100,
      "target2": 63800,
      "stoploss": 49000,
      "rrRatio": 2.0,
      "atr": 3364,
      "riskPct": 7.0,
      "momentum": 100,
      "conditionsMet": [
        "T1.200MA위",
        "T2.150MA위",
        "T3.50MA위",
        "T4.정배열",
        "T5.200MA상승",
        "T6.52주98%",
        "T7.저점+25%",
        "T8.거래량1.9x",
        "T9.양봉",
        "T10.전일↑",
        "T11.캔들양호",
        "T12.주가5천↑",
        "T13.거래대금82억",
        "T14.시총1천억↑",
        "B2.MACD가속↑",
        "B3.52주신고가98%",
        "B5.Stoch상승94",
        "B6.OBV매집",
        "B7.BB상단돌파101%",
        "B8.장대양봉",
        "B9.10MA돌파",
        "B10.RS강49%",
        "B11.거래증가1.9x",
        "S6.쌍끌이매수",
        "S10.업종강세100%"
      ],
      "conditionsDetail": "23/25",
      "rsi": 78.6,
      "macdHist": 1136.13,
      "volumeRatio": 1.9,
      "dataDate": "2026-05-04",
      "changeRate": 14.97,
      "foreignNet5d": 19669,
      "instNet5d": 9732,
      "foreignHold": 7.08,
      "foreignBuyDays": 3,
      "instBuyDays": 2,
      "per": 62.99,
      "pbr": 5.7,
      "eps": 835.0,
      "divYield": 0.0,
      "targetPrice": 0.0,
      "recommMean": 0.0,
      "sectorRatio": 100.0,
      "high52w": 53700.0,
      "low52w": 11700.0,
      "pos52w": 97.4,
      "distFromHigh": 2.0,
      "atrRatio": 1.16,
      "squeeze": false,
      "vwapDist": 32.6,
      "cmf": 0.328,
      "rocAccel": 10.88,
      "compression": 0.59,
      "insideDays": 2,
      "z20": 2.06,
      "z60": 3.18,
      "adx": 71.6,
      "rSquared": 0.96,
      "trendSlope": 1068.0,
      "advancedTotal": 15,
      "f1_score": -5,
      "f2_score": 0,
      "f3_score": 0,
      "f4_score": 7,
      "f5_score": 6,
      "f6_score": 4,
      "f7_score": 0,
      "f8_score": 0,
      "f9_score": -3,
      "f10_score": 6,
      "rankScore": 67.8,
      "rank": 16
    },
    {
      "code": "007340",
      "name": "DN오토모티브",
      "market": "KOSPI",
      "close": 51100,
      "open": 48000,
      "high": 52700,
      "low": 45950,
      "volume": 553340,
      "marketCap": 29899,
      "buyPrice": 51200,
      "target1": 58400,
      "target2": 62000,
      "stoploss": 47600,
      "rrRatio": 2.0,
      "atr": 3386,
      "riskPct": 7.0,
      "momentum": 100,
      "conditionsMet": [
        "T1.200MA위",
        "T2.150MA위",
        "T3.50MA위",
        "T4.정배열",
        "T5.200MA상승",
        "T6.52주97%",
        "T7.저점+25%",
        "T8.거래량1.6x",
        "T9.양봉",
        "T10.전일↑",
        "T11.캔들양호",
        "T12.주가5천↑",
        "T13.거래대금283억",
        "T14.시총1천억↑",
        "B1.RSI최적74",
        "B2.MACD가속↑",
        "B3.52주근접97%",
        "B6.OBV매집",
        "B7.BB상단돌파116%",
        "B9.10MA돌파",
        "B10.RS강100%",
        "B11.거래증가1.6x",
        "S6.쌍끌이매수",
        "S8.PER10.6",
        "S10.업종강세100%"
      ],
      "conditionsDetail": "22/25",
      "rsi": 73.6,
      "macdHist": 939.83,
      "volumeRatio": 1.6,
      "dataDate": "2026-05-04",
      "changeRate": 6.35,
      "foreignNet5d": 39868,
      "instNet5d": 93034,
      "foreignHold": 4.21,
      "foreignBuyDays": 3,
      "instBuyDays": 4,
      "per": 10.63,
      "pbr": 1.32,
      "eps": 4809.0,
      "divYield": 1.96,
      "targetPrice": 50000.0,
      "recommMean": 4.0,
      "sectorRatio": 100.0,
      "high52w": 52900.0,
      "low52w": 19950.0,
      "pos52w": 95.1,
      "distFromHigh": 3.0,
      "atrRatio": 1.3,
      "squeeze": false,
      "vwapDist": 26.4,
      "cmf": 0.181,
      "rocAccel": 8.2,
      "compression": 0.76,
      "insideDays": 2,
      "z20": 2.63,
      "z60": 2.63,
      "adx": 87.0,
      "rSquared": 0.77,
      "trendSlope": 650.8,
      "advancedTotal": 11,
      "f1_score": -5,
      "f2_score": 0,
      "f3_score": 0,
      "f4_score": 7,
      "f5_score": 6,
      "f6_score": 0,
      "f7_score": 0,
      "f8_score": 0,
      "f9_score": -3,
      "f10_score": 6,
      "rankScore": 67.6,
      "rank": 17
    },
    {
      "code": "327260",
      "name": "RF머트리얼즈",
      "market": "KOSDAQ",
      "close": 108600,
      "open": 98000,
      "high": 112500,
      "low": 98000,
      "volume": 707452,
      "marketCap": 9226,
      "buyPrice": 108900,
      "target1": 120400,
      "target2": 132000,
      "stoploss": 101200,
      "rrRatio": 1.49,
      "atr": 12436,
      "riskPct": 7.1,
      "momentum": 100,
      "conditionsMet": [
        "T1.200MA위",
        "T2.150MA위",
        "T3.50MA위",
        "T4.정배열",
        "T5.200MA상승",
        "T6.52주93%",
        "T7.저점+25%",
        "T8.거래량1.6x",
        "T9.양봉",
        "T10.전일↑",
        "T11.캔들양호",
        "T12.주가5천↑",
        "T13.거래대금768억",
        "T14.시총1천억↑",
        "B1.RSI최적65",
        "B2.MACD반전",
        "B3.52주근접93%",
        "B5.Stoch골든77",
        "B6.OBV매집",
        "B7.BB상단87%",
        "B8.장대양봉",
        "B9.10MA돌파",
        "B10.RS강242%",
        "B11.거래증가1.6x",
        "S6.쌍끌이매수",
        "S7.외인13%",
        "S9.목표+38%",
        "S10.업종강세83%"
      ],
      "conditionsDetail": "24/25",
      "rsi": 65.4,
      "macdHist": -971.92,
      "volumeRatio": 1.6,
      "dataDate": "2026-05-04",
      "changeRate": 16.4,
      "foreignNet5d": 212200,
      "instNet5d": 19596,
      "foreignHold": 12.52,
      "foreignBuyDays": 5,
      "instBuyDays": 2,
      "per": 129.75,
      "pbr": 17.35,
      "eps": 837.0,
      "divYield": 0.0,
      "targetPrice": 150000.0,
      "recommMean": 4.0,
      "sectorRatio": 83.33333333333334,
      "high52w": 116900.0,
      "low52w": 5150.0,
      "pos52w": 92.6,
      "distFromHigh": 7.1,
      "atrRatio": 1.32,
      "squeeze": false,
      "vwapDist": 18.5,
      "cmf": 0.0,
      "rocAccel": 8.06,
      "compression": 0.75,
      "insideDays": 3,
      "z20": 1.5,
      "z60": 1.92,
      "adx": 31.2,
      "rSquared": 0.28,
      "trendSlope": 971.6,
      "advancedTotal": 13,
      "f1_score": -2,
      "f2_score": 0,
      "f3_score": 0,
      "f4_score": 2,
      "f5_score": 6,
      "f6_score": 0,
      "f7_score": 6,
      "f8_score": 0,
      "f9_score": 1,
      "f10_score": 0,
      "rankScore": 66.4,
      "rank": 18
    },
    {
      "code": "003530",
      "name": "한화투자증권",
      "market": "KOSPI",
      "close": 8190,
      "open": 7650,
      "high": 8600,
      "low": 7630,
      "volume": 19713752,
      "marketCap": 17571,
      "buyPrice": 8210,
      "target1": 9080,
      "target2": 9950,
      "stoploss": 7630,
      "rrRatio": 1.5,
      "atr": 402,
      "riskPct": 7.1,
      "momentum": 100,
      "conditionsMet": [
        "T1.200MA위",
        "T2.150MA위",
        "T3.50MA위",
        "T4.정배열",
        "T5.200MA상승",
        "T6.52주80%",
        "T7.저점+25%",
        "T8.거래량2.7x",
        "T9.양봉",
        "T10.전일↑",
        "T11.캔들양호",
        "T12.주가5천↑",
        "T13.거래대금1615억",
        "T14.시총1천억↑",
        "B1.RSI최적61",
        "B2.MACD가속↑",
        "B5.Stoch골든72",
        "B6.OBV매집",
        "B7.BB상단돌파90%",
        "B8.양봉양호",
        "B9.10MA돌파",
        "B10.RS강34%",
        "B11.거래급증2.7x",
        "S6.외인매수3일",
        "S8.PER17.6",
        "S10.업종강세100%"
      ],
      "conditionsDetail": "23/25",
      "rsi": 60.9,
      "macdHist": 44.81,
      "volumeRatio": 3.2,
      "dataDate": "2026-05-04",
      "changeRate": 9.05,
      "foreignNet5d": 667405,
      "instNet5d": -104605,
      "foreignHold": 7.07,
      "foreignBuyDays": 3,
      "instBuyDays": 2,
      "per": 17.61,
      "pbr": 0.86,
      "eps": 465.0,
      "divYield": 0.0,
      "targetPrice": 0.0,
      "recommMean": 0.0,
      "sectorRatio": 100.0,
      "high52w": 10300.0,
      "low52w": 3450.0,
      "pos52w": 69.9,
      "distFromHigh": 20.5,
      "atrRatio": 0.68,
      "squeeze": false,
      "vwapDist": 6.1,
      "cmf": 0.07,
      "rocAccel": 1.11,
      "compression": 0.54,
      "insideDays": 3,
      "z20": 1.62,
      "z60": 1.16,
      "adx": 60.5,
      "rSquared": 0.79,
      "trendSlope": 66.3,
      "advancedTotal": 37,
      "f1_score": 5,
      "f2_score": 4,
      "f3_score": 2,
      "f4_score": 5,
      "f5_score": 4,
      "f6_score": 4,
      "f7_score": 6,
      "f8_score": 0,
      "f9_score": 1,
      "f10_score": 6,
      "rankScore": 66.1,
      "rank": 19
    },
    {
      "code": "272290",
      "name": "이녹스첨단소재",
      "market": "KOSDAQ",
      "close": 36300,
      "open": 35200,
      "high": 36700,
      "low": 34900,
      "volume": 458518,
      "marketCap": 7237,
      "buyPrice": 36400,
      "target1": 39150,
      "target2": 41950,
      "stoploss": 34550,
      "rrRatio": 1.49,
      "atr": 1675,
      "riskPct": 5.1,
      "momentum": 100,
      "conditionsMet": [
        "T1.200MA위",
        "T2.150MA위",
        "T3.50MA위",
        "T4.정배열",
        "T5.200MA상승",
        "T6.52주82%",
        "T7.저점+25%",
        "T8.거래량1.5x",
        "T9.양봉",
        "T10.전일↑",
        "T11.캔들양호",
        "T12.주가5천↑",
        "T13.거래대금166억",
        "T14.시총1천억↑",
        "B1.RSI최적59",
        "B2.MACD가속↑",
        "B5.Stoch상승82",
        "B6.OBV매집",
        "B7.BB상단76%",
        "B8.양봉양호",
        "B9.10MA돌파",
        "B10.RS양17%",
        "B11.거래증가1.5x",
        "S6.외인매수3일",
        "S8.PER12.6",
        "S9.목표+23%",
        "S10.업종강세83%"
      ],
      "conditionsDetail": "23/25",
      "rsi": 59.2,
      "macdHist": 139.56,
      "volumeRatio": 1.6,
      "dataDate": "2026-05-04",
      "changeRate": 5.83,
      "foreignNet5d": 40600,
      "instNet5d": -46748,
      "foreignHold": 8.62,
      "foreignBuyDays": 3,
      "instBuyDays": 2,
      "per": 12.64,
      "pbr": 1.74,
      "eps": 2871.0,
      "divYield": 0.96,
      "targetPrice": 44667.0,
      "recommMean": 4.0,
      "sectorRatio": 83.33333333333334,
      "high52w": 44400.0,
      "low52w": 20600.0,
      "pos52w": 64.6,
      "distFromHigh": 18.2,
      "atrRatio": 0.75,
      "squeeze": false,
      "vwapDist": 5.3,
      "cmf": 0.202,
      "rocAccel": -15.46,
      "compression": 0.31,
      "insideDays": 3,
      "z20": 1.04,
      "z60": 0.81,
      "adx": 34.3,
      "rSquared": 0.69,
      "trendSlope": 353.5,
      "advancedTotal": 35,
      "f1_score": 5,
      "f2_score": 4,
      "f3_score": 2,
      "f4_score": 7,
      "f5_score": -3,
      "f6_score": 7,
      "f7_score": 6,
      "f8_score": 0,
      "f9_score": 1,
      "f10_score": 6,
      "rankScore": 65.2,
      "rank": 20
    },
    {
      "code": "062040",
      "name": "산일전기",
      "market": "KOSPI",
      "close": 333500,
      "open": 279000,
      "high": 341000,
      "low": 277000,
      "volume": 2108306,
      "marketCap": 102104,
      "buyPrice": 334500,
      "target1": 381500,
      "target2": 405000,
      "stoploss": 311000,
      "rrRatio": 2.0,
      "atr": 21050,
      "riskPct": 7.0,
      "momentum": 100,
      "conditionsMet": [
        "T1.200MA위",
        "T2.150MA위",
        "T3.50MA위",
        "T4.정배열",
        "T5.200MA상승",
        "T6.52주98%",
        "T7.저점+25%",
        "T8.거래량3.9x",
        "T9.양봉",
        "T10.전일↑",
        "T11.캔들양호",
        "T12.주가5천↑",
        "T13.거래대금7031억",
        "T14.시총1천억↑",
        "B2.MACD가속↑",
        "B3.52주신고가98%",
        "B5.Stoch상승96",
        "B6.OBV매집",
        "B7.BB상단돌파121%",
        "B8.장대양봉",
        "B9.10MA돌파",
        "B10.RS강122%",
        "B11.거래폭발3.9x",
        "S6.기관매수4일",
        "S7.외인17%",
        "S10.업종강세100%"
      ],
      "conditionsDetail": "23/25",
      "rsi": 86.6,
      "macdHist": 10951.94,
      "volumeRatio": 3.8,
      "dataDate": "2026-05-04",
      "changeRate": 25.38,
      "foreignNet5d": -204827,
      "instNet5d": 147106,
      "foreignHold": 17.03,
      "foreignBuyDays": 2,
      "instBuyDays": 4,
      "per": 68.19,
      "pbr": 17.31,
      "eps": 4891.0,
      "divYield": 0.38,
      "targetPrice": 216556.0,
      "recommMean": 4.0,
      "sectorRatio": 100.0,
      "high52w": 341000.0,
      "low52w": 56900.0,
      "pos52w": 97.4,
      "distFromHigh": 2.2,
      "atrRatio": 1.52,
      "squeeze": false,
      "vwapDist": 54.9,
      "cmf": 0.35,
      "rocAccel": 23.72,
      "compression": 0.69,
      "insideDays": 1,
      "z20": 2.84,
      "z60": 4.56,
      "adx": 92.6,
      "rSquared": 0.84,
      "trendSlope": 7318.1,
      "advancedTotal": 17,
      "f1_score": -5,
      "f2_score": 0,
      "f3_score": 0,
      "f4_score": 7,
      "f5_score": 6,
      "f6_score": 0,
      "f7_score": 6,
      "f8_score": 0,
      "f9_score": -3,
      "f10_score": 6,
      "rankScore": 64.0,
      "rank": 21
    },
    {
      "code": "103590",
      "name": "일진전기",
      "market": "KOSPI",
      "close": 144100,
      "open": 131200,
      "high": 147900,
      "low": 129000,
      "volume": 2215806,
      "marketCap": 68715,
      "buyPrice": 144500,
      "target1": 164900,
      "target2": 175100,
      "stoploss": 134300,
      "rrRatio": 2.0,
      "atr": 8200,
      "riskPct": 7.1,
      "momentum": 100,
      "conditionsMet": [
        "T1.200MA위",
        "T2.150MA위",
        "T3.50MA위",
        "T4.정배열",
        "T5.200MA상승",
        "T6.52주97%",
        "T7.저점+25%",
        "T8.거래량4.0x",
        "T9.양봉",
        "T10.전일↑",
        "T11.캔들양호",
        "T12.주가5천↑",
        "T13.거래대금3193억",
        "T14.시총1천억↑",
        "B2.MACD가속↑",
        "B3.52주신고가97%",
        "B5.Stoch상승94",
        "B6.OBV매집",
        "B7.BB상단돌파118%",
        "B8.양봉양호",
        "B9.10MA돌파",
        "B10.RS강118%",
        "B11.거래폭발4.0x",
        "S6.기관매수5일",
        "S7.외인12%",
        "S10.업종강세100%"
      ],
      "conditionsDetail": "23/25",
      "rsi": 89.2,
      "macdHist": 5326.92,
      "volumeRatio": 4.0,
      "dataDate": "2026-05-04",
      "changeRate": 17.63,
      "foreignNet5d": -495291,
      "instNet5d": 552941,
      "foreignHold": 12.0,
      "foreignBuyDays": 2,
      "instBuyDays": 5,
      "per": 66.13,
      "pbr": 11.67,
      "eps": 2179.0,
      "divYield": 0.35,
      "targetPrice": 108800.0,
      "recommMean": 4.0,
      "sectorRatio": 100.0,
      "high52w": 149700.0,
      "low52w": 26050.0,
      "pos52w": 97.0,
      "distFromHigh": 2.6,
      "atrRatio": 1.31,
      "squeeze": false,
      "vwapDist": 38.3,
      "cmf": 0.165,
      "rocAccel": 48.03,
      "compression": 0.83,
      "insideDays": 0,
      "z20": 2.73,
      "z60": 4.36,
      "adx": 97.4,
      "rSquared": 0.78,
      "trendSlope": 2761.1,
      "advancedTotal": 17,
      "f1_score": -5,
      "f2_score": 0,
      "f3_score": 0,
      "f4_score": 7,
      "f5_score": 6,
      "f6_score": 0,
      "f7_score": 6,
      "f8_score": 0,
      "f9_score": -3,
      "f10_score": 6,
      "rankScore": 64.0,
      "rank": 22
    },
    {
      "code": "402340",
      "name": "SK스퀘어",
      "market": "KOSPI",
      "close": 991000,
      "open": 909000,
      "high": 998000,
      "low": 901000,
      "volume": 1195847,
      "marketCap": 1307708,
      "buyPrice": 993000,
      "target1": 1133000,
      "target2": 1203000,
      "stoploss": 923000,
      "rrRatio": 2.0,
      "atr": 51964,
      "riskPct": 7.0,
      "momentum": 100,
      "conditionsMet": [
        "T1.200MA위",
        "T2.150MA위",
        "T3.50MA위",
        "T4.정배열",
        "T5.200MA상승",
        "T6.52주99%",
        "T7.저점+25%",
        "T8.거래량2.0x",
        "T9.양봉",
        "T10.전일↑",
        "T11.캔들양호",
        "T12.주가5천↑",
        "T13.거래대금11851억",
        "T14.시총1천억↑",
        "B2.MACD가속↑",
        "B3.52주신고가99%",
        "B5.Stoch상승98",
        "B6.OBV매집",
        "B7.BB상단돌파110%",
        "B8.장대양봉",
        "B9.10MA돌파",
        "B10.RS강97%",
        "B11.거래증가2.0x",
        "S6.기관매수5일",
        "S7.외인50%",
        "S8.PER14.9",
        "S10.업종보통"
      ],
      "conditionsDetail": "23/25",
      "rsi": 85.7,
      "macdHist": 26536.53,
      "volumeRatio": 2.0,
      "dataDate": "2026-05-04",
      "changeRate": 17.84,
      "foreignNet5d": -209911,
      "instNet5d": 131150,
      "foreignHold": 49.78,
      "foreignBuyDays": 1,
      "instBuyDays": 5,
      "per": 14.91,
      "pbr": 4.73,
      "eps": 66468.0,
      "divYield": 0.0,
      "targetPrice": 861667.0,
      "recommMean": 4.0,
      "sectorRatio": 66.66666666666666,
      "high52w": 1016000.0,
      "low52w": 90600.0,
      "pos52w": 99.2,
      "distFromHigh": 0.7,
      "atrRatio": 1.13,
      "squeeze": false,
      "vwapDist": 37.9,
      "cmf": 0.076,
      "rocAccel": 17.67,
      "compression": 0.59,
      "insideDays": 1,
      "z20": 2.4,
      "z60": 3.81,
      "adx": 95.6,
      "rSquared": 0.93,
      "trendSlope": 20423.3,
      "advancedTotal": 19,
      "f1_score": -5,
      "f2_score": 0,
      "f3_score": 0,
      "f4_score": 5,
      "f5_score": 6,
      "f6_score": 4,
      "f7_score": 6,
      "f8_score": 0,
      "f9_score": -3,
      "f10_score": 6,
      "rankScore": 62.6,
      "rank": 23
    },
    {
      "code": "005940",
      "name": "NH투자증권",
      "market": "KOSPI",
      "close": 36450,
      "open": 34350,
      "high": 36500,
      "low": 33900,
      "volume": 2397495,
      "marketCap": 129888,
      "buyPrice": 36550,
      "target1": 39550,
      "target2": 42550,
      "stoploss": 34550,
      "rrRatio": 1.5,
      "atr": 1304,
      "riskPct": 5.5,
      "momentum": 100,
      "conditionsMet": [
        "T1.200MA위",
        "T2.150MA위",
        "T3.50MA위",
        "T4.정배열",
        "T5.200MA상승",
        "T6.52주86%",
        "T7.저점+25%",
        "T8.거래량2.0x",
        "T9.양봉",
        "T10.전일↑",
        "T11.캔들양호",
        "T12.주가5천↑",
        "T13.거래대금874억",
        "T14.시총1천억↑",
        "B1.RSI최적60",
        "B2.MACD반전",
        "B3.52주권내86%",
        "B5.Stoch상승98",
        "B6.OBV매집",
        "B7.BB상단82%",
        "B8.장대양봉",
        "B9.10MA돌파",
        "B10.RS강46%",
        "B11.거래증가2.0x",
        "S6.외인매수2일",
        "S7.외인12%",
        "S8.PER12.6",
        "S9.목표+15%",
        "S10.업종강세100%"
      ],
      "conditionsDetail": "24/25",
      "rsi": 60.3,
      "macdHist": -48.56,
      "volumeRatio": 2.1,
      "dataDate": "2026-05-04",
      "changeRate": 8.32,
      "foreignNet5d": 48386,
      "instNet5d": -196192,
      "foreignHold": 12.49,
      "foreignBuyDays": 2,
      "instBuyDays": 2,
      "per": 12.62,
      "pbr": 1.45,
      "eps": 2888.0,
      "divYield": 3.57,
      "targetPrice": 41972.0,
      "recommMean": 3.89,
      "sectorRatio": 100.0,
      "high52w": 44350.0,
      "low52w": 15160.0,
      "pos52w": 78.5,
      "distFromHigh": 14.4,
      "atrRatio": 0.64,
      "squeeze": true,
      "vwapDist": 5.5,
      "cmf": -0.025,
      "rocAccel": 0.17,
      "compression": 0.45,
      "insideDays": 2,
      "z20": 1.28,
      "z60": 1.18,
      "adx": 16.9,
      "rSquared": 0.41,
      "trendSlope": 168.5,
      "advancedTotal": 33,
      "f1_score": 5,
      "f2_score": 8,
      "f3_score": 2,
      "f4_score": 0,
      "f5_score": 4,
      "f6_score": 7,
      "f7_score": 6,
      "f8_score": 0,
      "f9_score": 1,
      "f10_score": 0,
      "rankScore": 62.1,
      "rank": 24
    },
    {
      "code": "229640",
      "name": "LS에코에너지",
      "market": "KOSPI",
      "close": 90400,
      "open": 87300,
      "high": 94300,
      "low": 84100,
      "volume": 782747,
      "marketCap": 27685,
      "buyPrice": 90600,
      "target1": 100200,
      "target2": 109800,
      "stoploss": 84200,
      "rrRatio": 1.5,
      "atr": 6271,
      "riskPct": 7.1,
      "momentum": 100,
      "conditionsMet": [
        "T1.200MA위",
        "T2.150MA위",
        "T3.50MA위",
        "T4.정배열",
        "T5.200MA상승",
        "T6.52주96%",
        "T7.저점+25%",
        "T8.거래량2.7x",
        "T9.양봉",
        "T10.전일↑",
        "T11.캔들양호",
        "T12.주가5천↑",
        "T13.거래대금708억",
        "T14.시총1천억↑",
        "B2.MACD가속↑",
        "B3.52주근접96%",
        "B5.Stoch상승92",
        "B6.OBV매집",
        "B7.BB상단돌파99%",
        "B9.10MA돌파",
        "B10.RS강115%",
        "B11.거래급증2.7x",
        "S6.기관매수5일",
        "S10.업종강세100%"
      ],
      "conditionsDetail": "22/25",
      "rsi": 84.4,
      "macdHist": 3781.0,
      "volumeRatio": 2.6,
      "dataDate": "2026-05-04",
      "changeRate": 3.79,
      "foreignNet5d": -154278,
      "instNet5d": 236340,
      "foreignHold": 6.58,
      "foreignBuyDays": 2,
      "instBuyDays": 5,
      "per": 65.79,
      "pbr": 13.11,
      "eps": 1374.0,
      "divYield": 0.28,
      "targetPrice": 72571.0,
      "recommMean": 4.0,
      "sectorRatio": 100.0,
      "high52w": 95400.0,
      "low52w": 31100.0,
      "pos52w": 93.8,
      "distFromHigh": 4.1,
      "atrRatio": 1.75,
      "squeeze": false,
      "vwapDist": 37.1,
      "cmf": 0.313,
      "rocAccel": 15.22,
      "compression": 0.74,
      "insideDays": 3,
      "z20": 1.97,
      "z60": 3.54,
      "adx": 100.0,
      "rSquared": 0.87,
      "trendSlope": 2496.0,
      "advancedTotal": 21,
      "f1_score": -2,
      "f2_score": 0,
      "f3_score": 0,
      "f4_score": 7,
      "f5_score": 6,
      "f6_score": 0,
      "f7_score": 3,
      "f8_score": 0,
      "f9_score": 1,
      "f10_score": 6,
      "rankScore": 61.3,
      "rank": 25
    },
    {
      "code": "000500",
      "name": "가온전선",
      "market": "KOSPI",
      "close": 288500,
      "open": 241500,
      "high": 310000,
      "low": 241500,
      "volume": 224530,
      "marketCap": 47727,
      "buyPrice": 289000,
      "target1": 330000,
      "target2": 350500,
      "stoploss": 268500,
      "rrRatio": 2.0,
      "atr": 24843,
      "riskPct": 7.1,
      "momentum": 100,
      "conditionsMet": [
        "T1.200MA위",
        "T2.150MA위",
        "T3.50MA위",
        "T4.정배열",
        "T5.200MA상승",
        "T6.52주93%",
        "T7.저점+25%",
        "T8.거래량2.4x",
        "T9.양봉",
        "T10.전일↑",
        "T11.캔들양호",
        "T12.주가5천↑",
        "T13.거래대금648억",
        "T14.시총1천억↑",
        "B2.MACD가속↑",
        "B3.52주근접93%",
        "B6.OBV매집",
        "B7.BB상단돌파106%",
        "B8.양봉양호",
        "B9.10MA돌파",
        "B10.RS강229%",
        "B11.거래급증2.4x",
        "S6.기관매수4일",
        "S10.업종강세100%"
      ],
      "conditionsDetail": "22/25",
      "rsi": 89.6,
      "macdHist": 12094.59,
      "volumeRatio": 2.4,
      "dataDate": "2026-05-04",
      "changeRate": 19.46,
      "foreignNet5d": -565,
      "instNet5d": 160259,
      "foreignHold": 1.22,
      "foreignBuyDays": 2,
      "instBuyDays": 4,
      "per": 89.68,
      "pbr": 9.87,
      "eps": 3217.0,
      "divYield": 0.04,
      "targetPrice": 0.0,
      "recommMean": 0.0,
      "sectorRatio": 100.0,
      "high52w": 310000.0,
      "low52w": 45300.0,
      "pos52w": 91.6,
      "distFromHigh": 6.9,
      "atrRatio": 2.14,
      "squeeze": false,
      "vwapDist": 61.4,
      "cmf": 0.322,
      "rocAccel": 6.61,
      "compression": 0.78,
      "insideDays": 0,
      "z20": 2.24,
      "z60": 3.79,
      "adx": 97.4,
      "rSquared": 0.92,
      "trendSlope": 9213.9,
      "advancedTotal": 14,
      "f1_score": -2,
      "f2_score": 0,
      "f3_score": 0,
      "f4_score": 7,
      "f5_score": 6,
      "f6_score": 0,
      "f7_score": 0,
      "f8_score": 0,
      "f9_score": -3,
      "f10_score": 6,
      "rankScore": 61.1,
      "rank": 26
    },
    {
      "code": "036200",
      "name": "유니셈",
      "market": "KOSDAQ",
      "close": 12170,
      "open": 11750,
      "high": 12410,
      "low": 11730,
      "volume": 733183,
      "marketCap": 3732,
      "buyPrice": 12200,
      "target1": 13080,
      "target2": 13970,
      "stoploss": 11610,
      "rrRatio": 1.49,
      "atr": 657,
      "riskPct": 4.8,
      "momentum": 100,
      "conditionsMet": [
        "T1.200MA위",
        "T2.150MA위",
        "T3.50MA위",
        "T4.정배열",
        "T5.200MA상승",
        "T6.52주97%",
        "T7.저점+25%",
        "T8.거래량2.0x",
        "T9.양봉",
        "T10.전일↑",
        "T11.캔들양호",
        "T12.주가5천↑",
        "T13.거래대금89억",
        "T14.시총1천억↑",
        "B1.RSI최적66",
        "B3.52주근접97%",
        "B5.Stoch상승80",
        "B6.OBV매집",
        "B7.BB상단80%",
        "B8.양봉양호",
        "B9.10MA돌파",
        "B10.RS양14%",
        "B11.거래급증2.0x",
        "S6.기관매수4일",
        "S7.외인15%",
        "S9.목표+19%",
        "S10.업종강세100%"
      ],
      "conditionsDetail": "23/25",
      "rsi": 65.5,
      "macdHist": 107.31,
      "volumeRatio": 2.1,
      "dataDate": "2026-05-04",
      "changeRate": 5.83,
      "foreignNet5d": -163518,
      "instNet5d": 48486,
      "foreignHold": 15.35,
      "foreignBuyDays": 3,
      "instBuyDays": 4,
      "per": 41.54,
      "pbr": 1.47,
      "eps": 293.0,
      "divYield": 0.66,
      "targetPrice": 14500.0,
      "recommMean": 4.0,
      "sectorRatio": 100.0,
      "high52w": 12920.0,
      "low52w": 5720.0,
      "pos52w": 93.8,
      "distFromHigh": 3.4,
      "atrRatio": 1.07,
      "squeeze": false,
      "vwapDist": 8.3,
      "cmf": 0.05,
      "rocAccel": -17.55,
      "compression": 0.44,
      "insideDays": 0,
      "z20": 1.21,
      "z60": 2.01,
      "adx": 72.9,
      "rSquared": 0.87,
      "trendSlope": 178.7,
      "advancedTotal": 14,
      "f1_score": -2,
      "f2_score": 0,
      "f3_score": 0,
      "f4_score": 2,
      "f5_score": -3,
      "f6_score": 4,
      "f7_score": 6,
      "f8_score": 0,
      "f9_score": 1,
      "f10_score": 6,
      "rankScore": 60.6,
      "rank": 27
    },
    {
      "code": "009160",
      "name": "SIMPAC",
      "market": "KOSPI",
      "close": 6440,
      "open": 5900,
      "high": 6790,
      "low": 5750,
      "volume": 1168262,
      "marketCap": 4210,
      "buyPrice": 6450,
      "target1": 7370,
      "target2": 7830,
      "stoploss": 5990,
      "rrRatio": 2.0,
      "atr": 351,
      "riskPct": 7.1,
      "momentum": 100,
      "conditionsMet": [
        "T1.200MA위",
        "T2.150MA위",
        "T3.50MA위",
        "T4.정배열",
        "T5.200MA상승",
        "T6.52주95%",
        "T7.저점+25%",
        "T8.거래량7.3x",
        "T9.양봉",
        "T10.전일↑",
        "T11.캔들양호",
        "T12.주가5천↑",
        "T13.거래대금75억",
        "T14.시총1천억↑",
        "B1.RSI최적68",
        "B2.MACD가속↑",
        "B3.52주근접95%",
        "B5.Stoch골든78",
        "B6.OBV매집",
        "B7.BB상단돌파118%",
        "B8.양봉양호",
        "B9.10MA돌파",
        "B10.RS강30%",
        "B11.거래폭발7.3x",
        "S6.기관매수2일",
        "S8.PER20.4",
        "S10.업종보통"
      ],
      "conditionsDetail": "24/25",
      "rsi": 68.4,
      "macdHist": 81.36,
      "volumeRatio": 7.2,
      "dataDate": "2026-05-04",
      "changeRate": 9.71,
      "foreignNet5d": -230116,
      "instNet5d": 5772,
      "foreignHold": 2.28,
      "foreignBuyDays": 0,
      "instBuyDays": 2,
      "per": 20.44,
      "pbr": 0.53,
      "eps": 315.0,
      "divYield": 4.66,
      "targetPrice": 0.0,
      "recommMean": 0.0,
      "sectorRatio": 66.66666666666666,
      "high52w": 6790.0,
      "low52w": 3980.0,
      "pos52w": 87.7,
      "distFromHigh": 5.2,
      "atrRatio": 1.31,
      "squeeze": false,
      "vwapDist": 9.8,
      "cmf": 0.041,
      "rocAccel": 12.27,
      "compression": 0.91,
      "insideDays": 3,
      "z20": 2.74,
      "z60": 3.59,
      "adx": 65.4,
      "rSquared": 0.65,
      "trendSlope": 45.2,
      "advancedTotal": 9,
      "f1_score": -2,
      "f2_score": 0,
      "f3_score": 0,
      "f4_score": 2,
      "f5_score": 6,
      "f6_score": 0,
      "f7_score": 0,
      "f8_score": 0,
      "f9_score": -3,
      "f10_score": 6,
      "rankScore": 60.2,
      "rank": 28
    },
    {
      "code": "006260",
      "name": "LS",
      "market": "KOSPI",
      "close": 509000,
      "open": 502000,
      "high": 515000,
      "low": 485500,
      "volume": 369776,
      "marketCap": 158808,
      "buyPrice": 510000,
      "target1": 570000,
      "target2": 600000,
      "stoploss": 480000,
      "rrRatio": 2.0,
      "atr": 30571,
      "riskPct": 5.9,
      "momentum": 100,
      "conditionsMet": [
        "T1.200MA위",
        "T2.150MA위",
        "T3.50MA위",
        "T4.정배열",
        "T5.200MA상승",
        "T6.52주99%",
        "T7.저점+25%",
        "T8.거래량1.9x",
        "T9.양봉",
        "T10.전일↑",
        "T11.캔들양호",
        "T12.주가5천↑",
        "T13.거래대금1882억",
        "T14.시총1천억↑",
        "B2.MACD가속↑",
        "B3.52주신고가99%",
        "B5.Stoch상승97",
        "B6.OBV매집",
        "B7.BB상단돌파109%",
        "B9.10MA돌파",
        "B10.RS강132%",
        "B11.거래증가1.9x",
        "S6.기관매수4일",
        "S7.외인18%",
        "S10.업종강세100%"
      ],
      "conditionsDetail": "22/25",
      "rsi": 82.6,
      "macdHist": 14579.57,
      "volumeRatio": 1.9,
      "dataDate": "2026-05-04",
      "changeRate": 12.36,
      "foreignNet5d": -224096,
      "instNet5d": 61859,
      "foreignHold": 18.21,
      "foreignBuyDays": 0,
      "instBuyDays": 4,
      "per": 60.18,
      "pbr": 2.78,
      "eps": 8458.0,
      "divYield": 0.49,
      "targetPrice": 371550.0,
      "recommMean": 4.0,
      "sectorRatio": 100.0,
      "high52w": 563000.0,
      "low52w": 123900.0,
      "pos52w": 98.5,
      "distFromHigh": 1.2,
      "atrRatio": 1.38,
      "squeeze": false,
      "vwapDist": 38.4,
      "cmf": 0.076,
      "rocAccel": 18.7,
      "compression": 0.71,
      "insideDays": 1,
      "z20": 2.37,
      "z60": 3.62,
      "adx": 84.4,
      "rSquared": 0.91,
      "trendSlope": 10812.0,
      "advancedTotal": 15,
      "f1_score": -5,
      "f2_score": 0,
      "f3_score": 0,
      "f4_score": 5,
      "f5_score": 6,
      "f6_score": 0,
      "f7_score": 6,
      "f8_score": 0,
      "f9_score": -3,
      "f10_score": 6,
      "rankScore": 59.4,
      "rank": 29
    },
    {
      "code": "394280",
      "name": "오픈엣지테크놀로지",
      "market": "KOSDAQ",
      "close": 21800,
      "open": 21500,
      "high": 22100,
      "low": 21200,
      "volume": 577982,
      "marketCap": 5744,
      "buyPrice": 21850,
      "target1": 23200,
      "target2": 24550,
      "stoploss": 20950,
      "rrRatio": 1.5,
      "atr": 1406,
      "riskPct": 4.1,
      "momentum": 100,
      "conditionsMet": [
        "T1.200MA위",
        "T2.150MA위",
        "T3.50MA위",
        "T4.정배열",
        "T5.200MA상승",
        "T6.52주98%",
        "T7.저점+25%",
        "T8.거래량1.5x",
        "T9.양봉",
        "T10.전일↑",
        "T11.캔들양호",
        "T12.주가5천↑",
        "T13.거래대금126억",
        "T14.시총1천억↑",
        "B1.RSI최적69",
        "B2.MACD가속↑",
        "B3.52주신고가98%",
        "B5.Stoch상승93",
        "B6.OBV매집",
        "B7.BB상단돌파91%",
        "B9.10MA돌파",
        "B10.RS강49%",
        "B11.거래증가1.5x",
        "S6.기관매수4일",
        "S9.목표+28%",
        "S10.업종강세100%"
      ],
      "conditionsDetail": "23/25",
      "rsi": 69.4,
      "macdHist": 352.55,
      "volumeRatio": 1.5,
      "dataDate": "2026-05-04",
      "changeRate": 6.6,
      "foreignNet5d": -159520,
      "instNet5d": 56863,
      "foreignHold": 3.71,
      "foreignBuyDays": 1,
      "instBuyDays": 4,
      "per": 0.0,
      "pbr": 31.92,
      "eps": -1208.0,
      "divYield": 0.0,
      "targetPrice": 28000.0,
      "recommMean": 4.0,
      "sectorRatio": 100.0,
      "high52w": 23600.0,
      "low52w": 10310.0,
      "pos52w": 96.6,
      "distFromHigh": 1.8,
      "atrRatio": 1.05,
      "squeeze": false,
      "vwapDist": 15.5,
      "cmf": 0.101,
      "rocAccel": -3.33,
      "compression": 0.68,
      "insideDays": 0,
      "z20": 1.63,
      "z60": 2.61,
      "adx": 83.7,
      "rSquared": 0.93,
      "trendSlope": 374.0,
      "advancedTotal": 8,
      "f1_score": -5,
      "f2_score": 0,
      "f3_score": 0,
      "f4_score": 5,
      "f5_score": -3,
      "f6_score": 0,
      "f7_score": 4,
      "f8_score": 0,
      "f9_score": 1,
      "f10_score": 6,
      "rankScore": 59.4,
      "rank": 30
    },
    {
      "code": "178920",
      "name": "PI첨단소재",
      "market": "KOSPI",
      "close": 30500,
      "open": 27450,
      "high": 31800,
      "low": 27300,
      "volume": 1324425,
      "marketCap": 8957,
      "buyPrice": 30550,
      "target1": 34850,
      "target2": 37000,
      "stoploss": 28400,
      "rrRatio": 2.0,
      "atr": 1529,
      "riskPct": 7.0,
      "momentum": 100,
      "conditionsMet": [
        "T1.200MA위",
        "T2.150MA위",
        "T3.50MA위",
        "T4.정배열",
        "T5.200MA상승",
        "T6.52주96%",
        "T7.저점+25%",
        "T8.거래량4.1x",
        "T9.양봉",
        "T10.전일↑",
        "T11.캔들양호",
        "T12.주가5천↑",
        "T13.거래대금404억",
        "T14.시총1천억↑",
        "B1.RSI최적75",
        "B2.MACD가속↑",
        "B3.52주근접96%",
        "B5.Stoch상승84",
        "B6.OBV매집",
        "B7.BB상단돌파115%",
        "B8.양봉양호",
        "B9.10MA돌파",
        "B10.RS강85%",
        "B11.거래폭발4.1x",
        "S6.외인매수5일",
        "S7.외인11%",
        "S10.업종보통"
      ],
      "conditionsDetail": "24/25",
      "rsi": 74.9,
      "macdHist": 256.78,
      "volumeRatio": 4.1,
      "dataDate": "2026-05-04",
      "changeRate": 18.45,
      "foreignNet5d": 382591,
      "instNet5d": -106004,
      "foreignHold": 11.38,
      "foreignBuyDays": 5,
      "instBuyDays": 1,
      "per": 29.47,
      "pbr": 2.52,
      "eps": 1035.0,
      "divYield": 1.15,
      "targetPrice": 30667.0,
      "recommMean": 4.0,
      "sectorRatio": 66.66666666666666,
      "high52w": 31800.0,
      "low52w": 12030.0,
      "pos52w": 92.3,
      "distFromHigh": 4.1,
      "atrRatio": 0.96,
      "squeeze": false,
      "vwapDist": 17.0,
      "cmf": 0.239,
      "rocAccel": 5.95,
      "compression": 0.66,
      "insideDays": 0,
      "z20": 2.62,
      "z60": 3.02,
      "adx": 81.6,
      "rSquared": 0.81,
      "trendSlope": 326.1,
      "advancedTotal": 20,
      "f1_score": -2,
      "f2_score": 0,
      "f3_score": 0,
      "f4_score": 7,
      "f5_score": 6,
      "f6_score": 0,
      "f7_score": 6,
      "f8_score": 0,
      "f9_score": -3,
      "f10_score": 6,
      "rankScore": 59.0,
      "rank": 31
    },
    {
      "code": "010120",
      "name": "LS ELECTRIC",
      "market": "KOSPI",
      "close": 294000,
      "open": 286500,
      "high": 296500,
      "low": 281000,
      "volume": 1490046,
      "marketCap": 441000,
      "buyPrice": 294500,
      "target1": 327500,
      "target2": 344000,
      "stoploss": 278000,
      "rrRatio": 2.0,
      "atr": 16250,
      "riskPct": 5.6,
      "momentum": 100,
      "conditionsMet": [
        "T1.200MA위",
        "T2.150MA위",
        "T3.50MA위",
        "T4.정배열",
        "T5.200MA상승",
        "T6.52주99%",
        "T7.저점+25%",
        "T8.거래량1.5x",
        "T9.양봉",
        "T10.전일↑",
        "T11.캔들양호",
        "T12.주가5천↑",
        "T13.거래대금4381억",
        "T14.시총1천억↑",
        "B2.MACD가속↑",
        "B3.52주신고가99%",
        "B5.Stoch상승98",
        "B6.OBV매집",
        "B7.BB상단돌파100%",
        "B9.10MA돌파",
        "B10.RS강157%",
        "B11.거래증가1.5x",
        "S6.기관매수4일",
        "S7.외인20%",
        "S10.업종강세100%"
      ],
      "conditionsDetail": "22/25",
      "rsi": 89.4,
      "macdHist": 10087.91,
      "volumeRatio": 1.5,
      "dataDate": "2026-05-04",
      "changeRate": 5.76,
      "foreignNet5d": -1803985,
      "instNet5d": 330476,
      "foreignHold": 19.75,
      "foreignBuyDays": 0,
      "instBuyDays": 4,
      "per": 153.85,
      "pbr": 21.12,
      "eps": 1911.0,
      "divYield": 1.02,
      "targetPrice": 241692.0,
      "recommMean": 4.0,
      "sectorRatio": 100.0,
      "high52w": 296500.0,
      "low52w": 42100.0,
      "pos52w": 99.0,
      "distFromHigh": 0.8,
      "atrRatio": 1.34,
      "squeeze": false,
      "vwapDist": 33.0,
      "cmf": -0.107,
      "rocAccel": 13.92,
      "compression": 0.8,
      "insideDays": 1,
      "z20": 2.0,
      "z60": 3.26,
      "adx": 93.8,
      "rSquared": 0.87,
      "trendSlope": 7085.5,
      "advancedTotal": 10,
      "f1_score": -5,
      "f2_score": 0,
      "f3_score": 0,
      "f4_score": 0,
      "f5_score": 6,
      "f6_score": 0,
      "f7_score": 6,
      "f8_score": 0,
      "f9_score": -3,
      "f10_score": 6,
      "rankScore": 56.6,
      "rank": 32
    },
    {
      "code": "138080",
      "name": "오이솔루션",
      "market": "KOSDAQ",
      "close": 45050,
      "open": 40000,
      "high": 47850,
      "low": 40000,
      "volume": 2556491,
      "marketCap": 5576,
      "buyPrice": 45150,
      "target1": 49950,
      "target2": 54750,
      "stoploss": 41950,
      "rrRatio": 1.5,
      "atr": 4179,
      "riskPct": 7.1,
      "momentum": 100,
      "conditionsMet": [
        "T1.200MA위",
        "T2.150MA위",
        "T3.50MA위",
        "T4.정배열",
        "T5.200MA상승",
        "T6.52주89%",
        "T7.저점+25%",
        "T8.거래량2.3x",
        "T9.양봉",
        "T10.전일↑",
        "T11.캔들양호",
        "T12.주가5천↑",
        "T13.거래대금1152억",
        "T14.시총1천억↑",
        "B1.RSI최적59",
        "B2.MACD반전",
        "B3.52주권내89%",
        "B5.Stoch골든60",
        "B6.OBV매집",
        "B7.BB상단70%",
        "B8.양봉양호",
        "B9.10MA돌파",
        "B10.RS강174%",
        "B11.거래급증2.3x",
        "S6.외인매수3일",
        "S9.목표+33%",
        "S10.업종강세100%"
      ],
      "conditionsDetail": "24/25",
      "rsi": 59.1,
      "macdHist": -949.5,
      "volumeRatio": 2.3,
      "dataDate": "2026-05-04",
      "changeRate": 16.41,
      "foreignNet5d": 570368,
      "instNet5d": -312285,
      "foreignHold": 6.14,
      "foreignBuyDays": 3,
      "instBuyDays": 1,
      "per": 0.0,
      "pbr": 7.8,
      "eps": -2504.0,
      "divYield": 0.0,
      "targetPrice": 60000.0,
      "recommMean": 4.0,
      "sectorRatio": 100.0,
      "high52w": 50800.0,
      "low52w": 8600.0,
      "pos52w": 86.4,
      "distFromHigh": 11.3,
      "atrRatio": 1.1,
      "squeeze": false,
      "vwapDist": 5.8,
      "cmf": 0.027,
      "rocAccel": 0.05,
      "compression": 1.0,
      "insideDays": 1,
      "z20": 0.82,
      "z60": 1.22,
      "adx": 29.5,
      "rSquared": 0.0,
      "trendSlope": -6.8,
      "advancedTotal": 16,
      "f1_score": -2,
      "f2_score": 0,
      "f3_score": 2,
      "f4_score": 2,
      "f5_score": 4,
      "f6_score": 0,
      "f7_score": 6,
      "f8_score": 0,
      "f9_score": 4,
      "f10_score": 0,
      "rankScore": 56.6,
      "rank": 33
    },
    {
      "code": "230240",
      "name": "에치에프알",
      "market": "KOSDAQ",
      "close": 36600,
      "open": 31300,
      "high": 38350,
      "low": 31250,
      "volume": 2338736,
      "marketCap": 4871,
      "buyPrice": 36700,
      "target1": 41900,
      "target2": 44500,
      "stoploss": 34100,
      "rrRatio": 2.0,
      "atr": 2850,
      "riskPct": 7.1,
      "momentum": 100,
      "conditionsMet": [
        "T1.200MA위",
        "T2.150MA위",
        "T3.50MA위",
        "T4.정배열",
        "T5.200MA상승",
        "T6.52주95%",
        "T7.저점+25%",
        "T8.거래량3.4x",
        "T9.양봉",
        "T10.전일↑",
        "T11.캔들양호",
        "T12.주가5천↑",
        "T13.거래대금856억",
        "T14.시총1천억↑",
        "B1.RSI최적67",
        "B2.MACD가속↑",
        "B3.52주근접95%",
        "B5.Stoch상승87",
        "B6.OBV매집",
        "B7.BB상단돌파125%",
        "B8.장대양봉",
        "B10.RS강152%",
        "B11.거래폭발3.4x",
        "S6.외인매수5일",
        "S9.목표+37%",
        "S10.업종강세100%"
      ],
      "conditionsDetail": "23/25",
      "rsi": 67.3,
      "macdHist": 81.83,
      "volumeRatio": 3.4,
      "dataDate": "2026-05-04",
      "changeRate": 24.07,
      "foreignNet5d": 311264,
      "instNet5d": -63427,
      "foreignHold": 9.79,
      "foreignBuyDays": 5,
      "instBuyDays": 1,
      "per": 0.0,
      "pbr": 3.33,
      "eps": -23.0,
      "divYield": 0.0,
      "targetPrice": 50000.0,
      "recommMean": 4.0,
      "sectorRatio": 100.0,
      "high52w": 38350.0,
      "low52w": 11420.0,
      "pos52w": 93.5,
      "distFromHigh": 4.6,
      "atrRatio": 1.07,
      "squeeze": false,
      "vwapDist": 21.0,
      "cmf": -0.047,
      "rocAccel": 25.03,
      "compression": 1.0,
      "insideDays": 0,
      "z20": 3.01,
      "z60": 1.88,
      "adx": 52.0,
      "rSquared": 0.01,
      "trendSlope": 33.2,
      "advancedTotal": 7,
      "f1_score": -2,
      "f2_score": 0,
      "f3_score": 0,
      "f4_score": 0,
      "f5_score": 6,
      "f6_score": 0,
      "f7_score": 6,
      "f8_score": 0,
      "f9_score": -3,
      "f10_score": 0,
      "rankScore": 55.5,
      "rank": 34
    },
    {
      "code": "248070",
      "name": "솔루엠",
      "market": "KOSPI",
      "close": 20850,
      "open": 19450,
      "high": 21150,
      "low": 19450,
      "volume": 656974,
      "marketCap": 9970,
      "buyPrice": 20900,
      "target1": 22700,
      "target2": 24500,
      "stoploss": 19700,
      "rrRatio": 1.5,
      "atr": 791,
      "riskPct": 5.7,
      "momentum": 100,
      "conditionsMet": [
        "T1.200MA위",
        "T2.150MA위",
        "T3.50MA위",
        "T4.정배열",
        "T5.200MA상승",
        "T6.52주99%",
        "T7.저점+25%",
        "T8.거래량2.2x",
        "T9.양봉",
        "T10.전일↑",
        "T11.캔들양호",
        "T12.주가5천↑",
        "T13.거래대금137억",
        "T14.시총1천억↑",
        "B1.RSI최적67",
        "B2.MACD가속↑",
        "B3.52주신고가99%",
        "B5.Stoch상승89",
        "B6.OBV매집",
        "B7.BB상단86%",
        "B8.장대양봉",
        "B9.10MA돌파",
        "B10.RS강29%",
        "B11.거래급증2.2x",
        "S6.외인매수3일",
        "S7.외인20%",
        "S10.업종강세83%"
      ],
      "conditionsDetail": "24/25",
      "rsi": 67.5,
      "macdHist": 81.37,
      "volumeRatio": 2.2,
      "dataDate": "2026-05-04",
      "changeRate": 7.47,
      "foreignNet5d": 181223,
      "instNet5d": -46389,
      "foreignHold": 20.15,
      "foreignBuyDays": 3,
      "instBuyDays": 2,
      "per": 80.5,
      "pbr": 2.09,
      "eps": 259.0,
      "divYield": 0.36,
      "targetPrice": 23250.0,
      "recommMean": 4.0,
      "sectorRatio": 83.33333333333334,
      "high52w": 23650.0,
      "low52w": 14440.0,
      "pos52w": 95.5,
      "distFromHigh": 1.4,
      "atrRatio": 0.97,
      "squeeze": false,
      "vwapDist": 11.4,
      "cmf": 0.405,
      "rocAccel": -2.53,
      "compression": 0.41,
      "insideDays": 2,
      "z20": 1.45,
      "z60": 2.32,
      "adx": 60.1,
      "rSquared": 0.72,
      "trendSlope": 190.7,
      "advancedTotal": 13,
      "f1_score": -5,
      "f2_score": 0,
      "f3_score": 0,
      "f4_score": 7,
      "f5_score": -3,
      "f6_score": 7,
      "f7_score": 0,
      "f8_score": 0,
      "f9_score": 1,
      "f10_score": 6,
      "rankScore": 53.7,
      "rank": 35
    },
    {
      "code": "067310",
      "name": "하나마이크론",
      "market": "KOSDAQ",
      "close": 42050,
      "open": 40400,
      "high": 43850,
      "low": 40350,
      "volume": 3545894,
      "marketCap": 27948,
      "buyPrice": 42150,
      "target1": 45500,
      "target2": 48900,
      "stoploss": 39900,
      "rrRatio": 1.49,
      "atr": 2707,
      "riskPct": 5.3,
      "momentum": 100,
      "conditionsMet": [
        "T1.200MA위",
        "T2.150MA위",
        "T3.50MA위",
        "T4.정배열",
        "T5.200MA상승",
        "T6.52주96%",
        "T7.저점+25%",
        "T8.거래량1.7x",
        "T9.양봉",
        "T10.전일↑",
        "T11.캔들양호",
        "T12.주가5천↑",
        "T13.거래대금1491억",
        "T14.시총1천억↑",
        "B1.RSI최적67",
        "B2.MACD가속↑",
        "B3.52주근접96%",
        "B5.Stoch상승84",
        "B6.OBV매집",
        "B7.BB상단85%",
        "B9.10MA돌파",
        "B10.RS양16%",
        "B11.거래증가1.7x",
        "S6.외인매수4일",
        "S7.외인20%",
        "S10.업종강세100%"
      ],
      "conditionsDetail": "23/25",
      "rsi": 67.0,
      "macdHist": 561.71,
      "volumeRatio": 1.8,
      "dataDate": "2026-05-04",
      "changeRate": 5.92,
      "foreignNet5d": 759859,
      "instNet5d": -168291,
      "foreignHold": 19.7,
      "foreignBuyDays": 4,
      "instBuyDays": 2,
      "per": 73.13,
      "pbr": 7.0,
      "eps": 575.0,
      "divYield": 0.17,
      "targetPrice": 45000.0,
      "recommMean": 4.0,
      "sectorRatio": 100.0,
      "high52w": 43850.0,
      "low52w": 10030.0,
      "pos52w": 94.7,
      "distFromHigh": 4.1,
      "atrRatio": 1.03,
      "squeeze": false,
      "vwapDist": 13.3,
      "cmf": 0.05,
      "rocAccel": -13.36,
      "compression": 0.53,
      "insideDays": 3,
      "z20": 1.4,
      "z60": 2.35,
      "adx": 86.0,
      "rSquared": 0.93,
      "trendSlope": 726.1,
      "advancedTotal": 14,
      "f1_score": -2,
      "f2_score": 0,
      "f3_score": 0,
      "f4_score": 2,
      "f5_score": -3,
      "f6_score": 4,
      "f7_score": 6,
      "f8_score": 0,
      "f9_score": 1,
      "f10_score": 6,
      "rankScore": 50.6,
      "rank": 36
    },
    {
      "code": "059090",
      "name": "미코",
      "market": "KOSDAQ",
      "close": 26100,
      "open": 23900,
      "high": 27400,
      "low": 22900,
      "volume": 2538964,
      "marketCap": 8722,
      "buyPrice": 26150,
      "target1": 28900,
      "target2": 31700,
      "stoploss": 24300,
      "rrRatio": 1.49,
      "atr": 2231,
      "riskPct": 7.1,
      "momentum": 100,
      "conditionsMet": [
        "T1.200MA위",
        "T2.150MA위",
        "T3.50MA위",
        "T4.정배열",
        "T5.200MA상승",
        "T6.52주95%",
        "T7.저점+25%",
        "T8.거래량4.5x",
        "T9.양봉",
        "T10.전일↑",
        "T11.캔들양호",
        "T12.주가5천↑",
        "T13.거래대금663억",
        "T14.시총1천억↑",
        "B2.MACD가속↑",
        "B3.52주근접95%",
        "B5.Stoch상승90",
        "B6.OBV매집",
        "B7.BB상단돌파94%",
        "B9.10MA돌파",
        "B10.RS강60%",
        "B11.거래폭발4.5x",
        "S7.외인19%",
        "S10.업종강세100%"
      ],
      "conditionsDetail": "22/25",
      "rsi": 77.0,
      "macdHist": 481.88,
      "volumeRatio": 4.5,
      "dataDate": "2026-05-04",
      "changeRate": 15.23,
      "foreignNet5d": -135312,
      "instNet5d": -64131,
      "foreignHold": 19.07,
      "foreignBuyDays": 2,
      "instBuyDays": 1,
      "per": 29.56,
      "pbr": 7.14,
      "eps": 883.0,
      "divYield": 0.0,
      "targetPrice": 0.0,
      "recommMean": 0.0,
      "sectorRatio": 100.0,
      "high52w": 27400.0,
      "low52w": 10120.0,
      "pos52w": 92.6,
      "distFromHigh": 4.7,
      "atrRatio": 1.71,
      "squeeze": false,
      "vwapDist": 24.8,
      "cmf": 0.283,
      "rocAccel": -19.77,
      "compression": 0.5,
      "insideDays": 1,
      "z20": 1.78,
      "z60": 3.03,
      "adx": 78.3,
      "rSquared": 0.8,
      "trendSlope": 611.2,
      "advancedTotal": 19,
      "f1_score": -2,
      "f2_score": 0,
      "f3_score": 0,
      "f4_score": 7,
      "f5_score": -3,
      "f6_score": 4,
      "f7_score": 6,
      "f8_score": 0,
      "f9_score": 1,
      "f10_score": 6,
      "rankScore": 34.0,
      "rank": 37
    },
    {
      "code": "425040",
      "name": "티이엠씨",
      "market": "KOSDAQ",
      "close": 19710,
      "open": 17700,
      "high": 20350,
      "low": 17350,
      "volume": 10105156,
      "marketCap": 4204,
      "buyPrice": 19760,
      "target1": 22540,
      "target2": 23930,
      "stoploss": 18370,
      "rrRatio": 2.0,
      "atr": 1232,
      "riskPct": 7.0,
      "momentum": 100,
      "conditionsMet": [
        "T1.200MA위",
        "T2.150MA위",
        "T3.50MA위",
        "T4.정배열",
        "T5.200MA상승",
        "T6.52주97%",
        "T7.저점+25%",
        "T8.거래량4.0x",
        "T9.양봉",
        "T10.전일↑",
        "T11.캔들양호",
        "T12.주가5천↑",
        "T13.거래대금1992억",
        "T14.시총1천억↑",
        "B2.MACD가속↑",
        "B3.52주근접97%",
        "B5.Stoch상승92",
        "B6.OBV매집",
        "B7.BB상단돌파116%",
        "B8.양봉양호",
        "B9.10MA돌파",
        "B10.RS강111%",
        "B11.거래폭발4.0x",
        "S10.업종강세100%"
      ],
      "conditionsDetail": "23/25",
      "rsi": 80.1,
      "macdHist": 547.18,
      "volumeRatio": 3.9,
      "dataDate": "2026-05-04",
      "changeRate": 14.86,
      "foreignNet5d": -193189,
      "instNet5d": -23285,
      "foreignHold": 1.64,
      "foreignBuyDays": 1,
      "instBuyDays": 2,
      "per": 26.35,
      "pbr": 2.09,
      "eps": 748.0,
      "divYield": 0.76,
      "targetPrice": 0.0,
      "recommMean": 0.0,
      "sectorRatio": 100.0,
      "high52w": 20350.0,
      "low52w": 6000.0,
      "pos52w": 95.5,
      "distFromHigh": 3.1,
      "atrRatio": 1.26,
      "squeeze": false,
      "vwapDist": 23.8,
      "cmf": 0.008,
      "rocAccel": 61.32,
      "compression": 1.0,
      "insideDays": 0,
      "z20": 2.64,
      "z60": 3.32,
      "adx": 73.7,
      "rSquared": 0.3,
      "trendSlope": 195.1,
      "advancedTotal": 12,
      "f1_score": -5,
      "f2_score": 0,
      "f3_score": 0,
      "f4_score": 2,
      "f5_score": 6,
      "f6_score": 0,
      "f7_score": 6,
      "f8_score": 0,
      "f9_score": -3,
      "f10_score": 6,
      "rankScore": 33.2,
      "rank": 38
    },
    {
      "code": "389020",
      "name": "자람테크놀로지",
      "market": "KOSDAQ",
      "close": 57700,
      "open": 53000,
      "high": 63400,
      "low": 53000,
      "volume": 493607,
      "marketCap": 3845,
      "buyPrice": 57800,
      "target1": 63900,
      "target2": 70100,
      "stoploss": 53700,
      "rrRatio": 1.49,
      "atr": 4546,
      "riskPct": 7.1,
      "momentum": 100,
      "conditionsMet": [
        "T1.200MA위",
        "T2.150MA위",
        "T3.50MA위",
        "T4.정배열",
        "T5.200MA상승",
        "T6.52주89%",
        "T7.저점+25%",
        "T8.거래량2.1x",
        "T9.양봉",
        "T10.전일↑",
        "T11.캔들양호",
        "T12.주가5천↑",
        "T13.거래대금285억",
        "T14.시총1천억↑",
        "B1.RSI최적57",
        "B2.MACD반전",
        "B3.52주권내89%",
        "B5.Stoch골든47",
        "B6.OBV매집",
        "B7.BB상단76%",
        "B9.10MA돌파",
        "B10.RS강39%",
        "B11.거래급증2.1x",
        "S10.업종강세100%"
      ],
      "conditionsDetail": "23/25",
      "rsi": 57.2,
      "macdHist": -143.81,
      "volumeRatio": 2.1,
      "dataDate": "2026-05-04",
      "changeRate": 10.96,
      "foreignNet5d": -14453,
      "instNet5d": -30960,
      "foreignHold": 1.8,
      "foreignBuyDays": 1,
      "instBuyDays": 1,
      "per": 0.0,
      "pbr": 10.02,
      "eps": -1104.0,
      "divYield": 0.0,
      "targetPrice": 0.0,
      "recommMean": 0.0,
      "sectorRatio": 100.0,
      "high52w": 64900.0,
      "low52w": 30300.0,
      "pos52w": 79.2,
      "distFromHigh": 11.1,
      "atrRatio": 0.91,
      "squeeze": false,
      "vwapDist": 3.1,
      "cmf": -0.119,
      "rocAccel": -13.58,
      "compression": 0.61,
      "insideDays": 2,
      "z20": 1.03,
      "z60": 1.25,
      "adx": 45.1,
      "rSquared": 0.25,
      "trendSlope": 353.5,
      "advancedTotal": 15,
      "f1_score": 5,
      "f2_score": 0,
      "f3_score": 2,
      "f4_score": 0,
      "f5_score": -3,
      "f6_score": 0,
      "f7_score": 6,
      "f8_score": 0,
      "f9_score": 1,
      "f10_score": 4,
      "rankScore": 31.2,
      "rank": 39
    }
  ],
  "date": "2026-05-04",
  "timestamp": "2026-05-04 23:32:51",
  "mode": "KRX+Naver",
  "count": 39,
  "dayOfWeek": "월",
  "isTuesday": false,
  "tradeRules": {
    "slip": "0.3%",
    "t1SellRatio": "1/2",
    "t2SellRatio": "1/2",
    "trailingATR": 1.5,
    "maxHold": 20,
    "skipTuesday": true,
    "skip3Loss": true
  }
}