{
  "results": [
    {
      "code": "001800",
      "name": "오리온홀딩스",
      "market": "KOSPI",
      "close": 25800,
      "open": 25150,
      "high": 25850,
      "low": 24500,
      "volume": 70283,
      "marketCap": 16037,
      "buyPrice": 25800,
      "target1": 28350,
      "target2": 28350,
      "stoploss": 24000,
      "rrRatio": 1.42,
      "atr": 1643,
      "riskPct": 7.0,
      "momentum": 100,
      "conditionsMet": [
        "A1.종가>200MA",
        "A2.종가>60MA",
        "A3.정배열60>200",
        "A4.200MA상승",
        "B1.EPS+2149",
        "B2.PER11.9",
        "B3.목표+28%",
        "S6.외인매수5일",
        "S8.PER11.9",
        "S9.목표+28%"
      ],
      "conditionsDetail": "7/8",
      "rsi": 55.4,
      "macdHist": 2.76,
      "volumeRatio": 0.3,
      "dataDate": "2026-06-02",
      "changeRate": 3.02,
      "foreignNet5d": 155628,
      "instNet5d": -113687,
      "foreignHold": 9.7,
      "foreignBuyDays": 5,
      "instBuyDays": 0,
      "per": 11.91,
      "pbr": 0.62,
      "eps": 2149.0,
      "divYield": 4.3,
      "targetPrice": 33000.0,
      "recommMean": 4.0,
      "sectorRatio": 33.33333333333333,
      "high52w": 31150.0,
      "low52w": 18360.0,
      "pos52w": 65.4,
      "distFromHigh": 13.9,
      "atrRatio": 1.52,
      "squeeze": false,
      "vwapDist": 0.0,
      "cmf": 0.112,
      "rocAccel": -5.58,
      "compression": 0.29,
      "insideDays": 1,
      "z20": 0.84,
      "z60": 1.39,
      "adx": 59.4,
      "rSquared": 0.09,
      "trendSlope": 51.0,
      "advancedTotal": 21,
      "f1_score": 5,
      "f2_score": 0,
      "f3_score": 6,
      "f4_score": 5,
      "f5_score": -3,
      "f6_score": 4,
      "f7_score": 0,
      "f8_score": 0,
      "f9_score": 4,
      "f10_score": 0,
      "grade": "TREND",
      "p1Score": 0,
      "p1Details": [],
      "phase2Pass": false,
      "trigVolume": false,
      "trigPrice": false,
      "trigMA20": false,
      "trigMA60": false,
      "volMult": 0.29,
      "volTrendRatio": 0,
      "annualVol": 0,
      "bbWidthPct": 16.4,
      "boxRange": 0,
      "priceChg20": 0,
      "chgToday": 3.82,
      "tradingValueEok": 17.4,
      "minerviniCount": 0,
      "sector": "일반",
      "sectorBonus": 0,
      "finalScore": 95,
      "proCount": 0,
      "proFactors": [],
      "a1_52w": false,
      "a2_mom6m": false,
      "a3_vcp": false,
      "a4_volprice": false,
      "a5_pead": false,
      "a6_obv": false,
      "a7_trend": false,
      "a8_lowvol": false,
      "a9_rsi": false,
      "a10_base": false,
      "ret6m": 31.0,
      "annualVol60": 0,
      "gapHeld": false,
      "bbLowerBreak": false,
      "bbBreakClose": false,
      "bbBreakIntraday": false,
      "aCount": 4,
      "bCount": 3,
      "a1_ma200": true,
      "a2_ma60": true,
      "a3_align": true,
      "a4_ma200up": true,
      "b1_eps": true,
      "b2_per": true,
      "b3_target": true,
      "inLeadingSector": false,
      "huntTrigger": false,
      "breakoutTrigger": false,
      "d1_pullback": true,
      "d2_above_ma5": true,
      "d3_bullish": true,
      "d4_vol_pickup": false,
      "d5_rsi_ok": true,
      "f1_first_pullback": true,
      "pullbackCount": 2,
      "e1_new_high": false,
      "e2_vol_burst": false,
      "e3_price_up": true,
      "e4_rsi_ok": true,
      "e5_ma20_near": true,
      "k1_up_close": true,
      "k2_bullish": true,
      "k3_short_wick": true,
      "candlePass": true,
      "bodyRatio": 0.48,
      "upperWickRatio": 0.08,
      "ma20Dist": 3.44,
      "proximity52w": 86.1,
      "volMult5": 0.48,
      "volMult20": 0.29,
      "targetUpside": 27.9,
      "ret3m": 8.2,
      "maxHold": 6,
      "targetPct": 10,
      "isIntradayProxy": false,
      "rankScore": 95,
      "isAlternative": true,
      "rank": 1
    },
    {
      "code": "023530",
      "name": "롯데쇼핑",
      "market": "KOSPI",
      "close": 150100,
      "open": 143900,
      "high": 158100,
      "low": 142400,
      "volume": 84876,
      "marketCap": 42292,
      "buyPrice": 150100,
      "target1": 165100,
      "target2": 165100,
      "stoploss": 140400,
      "rrRatio": 1.55,
      "atr": 13064,
      "riskPct": 6.5,
      "momentum": 100,
      "conditionsMet": [
        "A1.종가>200MA",
        "A2.종가>60MA",
        "A3.정배열60>200",
        "A4.200MA상승",
        "B1.EPS+5782",
        "B2.PER25.9",
        "B3.목표+29%",
        "S6.외인매수5일",
        "S7.외인11%",
        "S9.목표+29%",
        "S10.업종보통"
      ],
      "conditionsDetail": "7/8",
      "rsi": 54.0,
      "macdHist": -2799.69,
      "volumeRatio": 0.5,
      "dataDate": "2026-06-02",
      "changeRate": 1.36,
      "foreignNet5d": 170440,
      "instNet5d": -109646,
      "foreignHold": 10.7,
      "foreignBuyDays": 5,
      "instBuyDays": 1,
      "per": 25.86,
      "pbr": 0.28,
      "eps": 5782.0,
      "divYield": 2.68,
      "targetPrice": 193846.0,
      "recommMean": 4.0,
      "sectorRatio": 50.0,
      "high52w": 186400.0,
      "low52w": 62700.0,
      "pos52w": 75.8,
      "distFromHigh": 15.7,
      "atrRatio": 1.5,
      "squeeze": false,
      "vwapDist": -1.3,
      "cmf": 0.109,
      "rocAccel": -14.67,
      "compression": 0.62,
      "insideDays": 0,
      "z20": -0.22,
      "z60": 1.11,
      "adx": 11.5,
      "rSquared": 0.12,
      "trendSlope": 666.0,
      "advancedTotal": 16,
      "f1_score": 5,
      "f2_score": 0,
      "f3_score": 4,
      "f4_score": 5,
      "f5_score": -3,
      "f6_score": 0,
      "f7_score": 0,
      "f8_score": 0,
      "f9_score": 4,
      "f10_score": 1,
      "grade": "TREND",
      "p1Score": 0,
      "p1Details": [],
      "phase2Pass": false,
      "trigVolume": false,
      "trigPrice": false,
      "trigMA20": false,
      "trigMA60": false,
      "volMult": 0.5,
      "volTrendRatio": 0,
      "annualVol": 0,
      "bbWidthPct": 30.0,
      "boxRange": 0,
      "priceChg20": 0,
      "chgToday": 1.76,
      "tradingValueEok": 124.3,
      "minerviniCount": 0,
      "sector": "일반",
      "sectorBonus": 0,
      "finalScore": 90,
      "proCount": 0,
      "proFactors": [],
      "a1_52w": false,
      "a2_mom6m": false,
      "a3_vcp": false,
      "a4_volprice": false,
      "a5_pead": false,
      "a6_obv": false,
      "a7_trend": false,
      "a8_lowvol": false,
      "a9_rsi": false,
      "a10_base": false,
      "ret6m": 109.6,
      "annualVol60": 0,
      "gapHeld": false,
      "bbLowerBreak": false,
      "bbBreakClose": false,
      "bbBreakIntraday": false,
      "aCount": 4,
      "bCount": 3,
      "a1_ma200": true,
      "a2_ma60": true,
      "a3_align": true,
      "a4_ma200up": true,
      "b1_eps": true,
      "b2_per": true,
      "b3_target": true,
      "inLeadingSector": false,
      "huntTrigger": false,
      "breakoutTrigger": false,
      "d1_pullback": false,
      "d2_above_ma5": true,
      "d3_bullish": true,
      "d4_vol_pickup": false,
      "d5_rsi_ok": true,
      "f1_first_pullback": true,
      "pullbackCount": 1,
      "e1_new_high": false,
      "e2_vol_burst": false,
      "e3_price_up": false,
      "e4_rsi_ok": true,
      "e5_ma20_near": true,
      "k1_up_close": true,
      "k2_bullish": true,
      "k3_short_wick": false,
      "candlePass": false,
      "bodyRatio": 0.39,
      "upperWickRatio": 1.29,
      "ma20Dist": -1.68,
      "proximity52w": 84.3,
      "volMult5": 0.62,
      "volMult20": 0.5,
      "targetUpside": 29.1,
      "ret3m": 39.4,
      "maxHold": 6,
      "targetPct": 10,
      "isIntradayProxy": false,
      "rankScore": 90,
      "isAlternative": true,
      "rank": 2
    },
    {
      "code": "001450",
      "name": "현대해상",
      "market": "KOSPI",
      "close": 34700,
      "open": 34150,
      "high": 34700,
      "low": 33400,
      "volume": 186094,
      "marketCap": 29411,
      "buyPrice": 34700,
      "target1": 38150,
      "target2": 38150,
      "stoploss": 33350,
      "rrRatio": 2.56,
      "atr": 2589,
      "riskPct": 3.9,
      "momentum": 100,
      "conditionsMet": [
        "A1.종가>200MA",
        "A2.종가>60MA",
        "A3.정배열60>200",
        "A4.200MA상승",
        "B1.EPS+11407",
        "B2.PER3.0",
        "B3.목표+19%",
        "C1.업종강세67%",
        "S6.쌍끌이매수",
        "S7.외인39%",
        "S8.PER3.0",
        "S9.목표+19%",
        "S10.업종보통"
      ],
      "conditionsDetail": "8/8",
      "rsi": 53.7,
      "macdHist": -205.99,
      "volumeRatio": 0.2,
      "dataDate": "2026-06-02",
      "changeRate": 0.29,
      "foreignNet5d": 21384,
      "instNet5d": 68075,
      "foreignHold": 38.99,
      "foreignBuyDays": 3,
      "instBuyDays": 4,
      "per": 3.02,
      "pbr": 0.52,
      "eps": 11407.0,
      "divYield": 0.0,
      "targetPrice": 41353.0,
      "recommMean": 3.76,
      "sectorRatio": 66.66666666666666,
      "high52w": 45550.0,
      "low52w": 23950.0,
      "pos52w": 56.6,
      "distFromHigh": 21.6,
      "atrRatio": 1.84,
      "squeeze": false,
      "vwapDist": -1.7,
      "cmf": 0.178,
      "rocAccel": -31.76,
      "compression": 0.64,
      "insideDays": 0,
      "z20": 0.18,
      "z60": 1.19,
      "adx": 27.3,
      "rSquared": 0.42,
      "trendSlope": 338.2,
      "advancedTotal": 19,
      "f1_score": 3,
      "f2_score": 0,
      "f3_score": 4,
      "f4_score": 7,
      "f5_score": -3,
      "f6_score": 0,
      "f7_score": 0,
      "f8_score": 0,
      "f9_score": 4,
      "f10_score": 4,
      "grade": "TREND",
      "p1Score": 0,
      "p1Details": [],
      "phase2Pass": false,
      "trigVolume": false,
      "trigPrice": false,
      "trigMA20": false,
      "trigMA60": false,
      "volMult": 0.17,
      "volTrendRatio": 0,
      "annualVol": 0,
      "bbWidthPct": 36.3,
      "boxRange": 0,
      "priceChg20": 0,
      "chgToday": 0.87,
      "tradingValueEok": 56.0,
      "minerviniCount": 0,
      "sector": "일반",
      "sectorBonus": 0,
      "finalScore": 90,
      "proCount": 5,
      "proFactors": [],
      "a1_52w": false,
      "a2_mom6m": false,
      "a3_vcp": false,
      "a4_volprice": false,
      "a5_pead": false,
      "a6_obv": false,
      "a7_trend": false,
      "a8_lowvol": false,
      "a9_rsi": false,
      "a10_base": false,
      "ret6m": 25.0,
      "annualVol60": 0,
      "gapHeld": false,
      "bbLowerBreak": false,
      "bbBreakClose": false,
      "bbBreakIntraday": false,
      "aCount": 4,
      "bCount": 3,
      "a1_ma200": true,
      "a2_ma60": true,
      "a3_align": true,
      "a4_ma200up": true,
      "b1_eps": true,
      "b2_per": true,
      "b3_target": true,
      "inLeadingSector": true,
      "huntTrigger": false,
      "breakoutTrigger": false,
      "d1_pullback": true,
      "d2_above_ma5": false,
      "d3_bullish": true,
      "d4_vol_pickup": false,
      "d5_rsi_ok": true,
      "f1_first_pullback": true,
      "pullbackCount": 0,
      "e1_new_high": false,
      "e2_vol_burst": false,
      "e3_price_up": false,
      "e4_rsi_ok": true,
      "e5_ma20_near": true,
      "k1_up_close": true,
      "k2_bullish": true,
      "k3_short_wick": true,
      "candlePass": true,
      "bodyRatio": 0.42,
      "upperWickRatio": 0.0,
      "ma20Dist": 1.65,
      "proximity52w": 78.4,
      "volMult5": 0.27,
      "volMult20": 0.17,
      "targetUpside": 19.2,
      "ret3m": 1.0,
      "maxHold": 6,
      "targetPct": 10,
      "isIntradayProxy": false,
      "rankScore": 90,
      "isAlternative": true,
      "rank": 3
    }
  ],
  "swingPicks": [],
  "date": "2026-06-02",
  "actualDataDate": "2026-06-02",
  "isHoliday": false,
  "dataStatus": "confirmed",
  "marketRegime": {
    "above_ma60": true,
    "close": 8555.56,
    "ma60": 6482.14,
    "ok": true
  },
  "strategyVersion": "2026.05.31b-stop10dlow-noPharmaBio-noPolitical-swingNo200-tp10-hold6-brkfirst-brk15tp-kospima60gate-ma20pos-vol15-rsi5070-Cbonus-F1-min3picks-altK1-pxcap20",
  "timestamp": "2026-06-02 11:05:29",
  "mode": "KRX+Naver",
  "count": 3,
  "dayOfWeek": "화",
  "isTuesday": true,
  "tradeRules": {
    "slip": "0.3%",
    "t1SellRatio": "1/2",
    "t2SellRatio": "1/2",
    "trailingATR": 1.5,
    "maxHold": 20,
    "skipTuesday": true,
    "skip3Loss": true
  }
}