{
  "results": [
    {
      "code": "014830",
      "name": "유니드",
      "market": "KOSPI",
      "close": 87800,
      "open": 86800,
      "high": 88600,
      "low": 85900,
      "volume": 37484,
      "marketCap": 5942,
      "buyPrice": 88000,
      "target1": 94000,
      "target2": 97000,
      "stoploss": 85000,
      "rrRatio": 2.0,
      "atr": 2771,
      "riskPct": 3.4,
      "momentum": 100,
      "conditionsMet": [
        "A.200MA돌파",
        "C.전일대비상승",
        "D.양봉",
        "E.가격적정",
        "F.BB하한돌파",
        "G.거래량2.2x",
        "H.60MA상승",
        "H2.정배열(1>10>20>200)",
        "I.MACD반전",
        "J.BB반등확인",
        "K.RSI64",
        "L.시총800억+",
        "M.양봉품질",
        "N.BB중심↑114%",
        "S0.W바닥",
        "S1.단기정배열",
        "S3.OBV매집",
        "S4.BB상단114%",
        "S6.쌍끌이매수",
        "S7.외인12%",
        "S8.PER9.1",
        "S9.목표+17%",
        "S10.업종보통"
      ],
      "conditionsDetail": "18/20",
      "rsi": 64.1,
      "macdHist": 431.99,
      "volumeRatio": 1.0,
      "dataDate": "2026-04-17",
      "changeRate": 3.66,
      "foreignNet5d": 15546,
      "instNet5d": 5011,
      "foreignHold": 11.95,
      "foreignBuyDays": 4,
      "instBuyDays": 4,
      "per": 9.11,
      "pbr": 0.54,
      "eps": 9643.0,
      "divYield": 2.28,
      "targetPrice": 102833.0,
      "recommMean": 4.0,
      "sectorRatio": 66.66666666666666,
      "high52w": 98200.0,
      "low52w": 62400.0,
      "pos52w": 70.4,
      "distFromHigh": 10.6,
      "atrRatio": 0.77,
      "squeeze": false,
      "vwapDist": 5.7,
      "cmf": 0.071,
      "rocAccel": 10.36,
      "compression": 0.88,
      "insideDays": 3,
      "z20": 2.55,
      "z60": 1.97,
      "adx": 63.0,
      "rSquared": 0.07,
      "trendSlope": 86.2,
      "advancedTotal": 25,
      "f1_score": 5,
      "f2_score": 4,
      "f3_score": 2,
      "f4_score": 5,
      "f5_score": 6,
      "f6_score": 0,
      "f7_score": 6,
      "f8_score": 0,
      "f9_score": -3,
      "f10_score": 0,
      "rankScore": 74.7,
      "rank": 1
    },
    {
      "code": "005490",
      "name": "POSCO홀딩스",
      "market": "KOSPI",
      "close": 382250,
      "open": 377000,
      "high": 386000,
      "low": 375500,
      "volume": 470366,
      "marketCap": 302901,
      "buyPrice": 383000,
      "target1": 406000,
      "target2": 417500,
      "stoploss": 371500,
      "rrRatio": 2.0,
      "atr": 13250,
      "riskPct": 3.0,
      "momentum": 100,
      "conditionsMet": [
        "A.200MA돌파",
        "C.전일대비상승",
        "D.양봉",
        "E.가격적정",
        "F.BB하한돌파",
        "G.거래량2.3x",
        "H.60MA상승",
        "H2.정배열(1>10>20>200)",
        "I.MACD반전",
        "J.BB반등확인",
        "K.RSI64",
        "L.시총800억+",
        "M.양봉품질",
        "N.BB중심↑102%",
        "S1.완전정배열",
        "S3.OBV매집",
        "S4.BB상단102%",
        "S5.양봉확인",
        "S6.기관매수3일",
        "S7.외인30%",
        "S9.목표+26%",
        "S10.업종보통"
      ],
      "conditionsDetail": "18/20",
      "rsi": 63.6,
      "macdHist": 3719.08,
      "volumeRatio": 1.0,
      "dataDate": "2026-04-17",
      "changeRate": 3.31,
      "foreignNet5d": -62015,
      "instNet5d": 30642,
      "foreignHold": 30.09,
      "foreignBuyDays": 1,
      "instBuyDays": 3,
      "per": 47.28,
      "pbr": 0.52,
      "eps": 8085.0,
      "divYield": 2.62,
      "targetPrice": 481647.0,
      "recommMean": 4.0,
      "sectorRatio": 66.66666666666666,
      "high52w": 427500.0,
      "low52w": 230000.0,
      "pos52w": 77.1,
      "distFromHigh": 10.6,
      "atrRatio": 0.81,
      "squeeze": false,
      "vwapDist": 8.6,
      "cmf": -0.078,
      "rocAccel": 2.42,
      "compression": 0.7,
      "insideDays": 0,
      "z20": 2.07,
      "z60": 1.13,
      "adx": 63.3,
      "rSquared": 0.82,
      "trendSlope": 2258.1,
      "advancedTotal": 20,
      "f1_score": 5,
      "f2_score": 4,
      "f3_score": 0,
      "f4_score": 0,
      "f5_score": 4,
      "f6_score": 0,
      "f7_score": 4,
      "f8_score": 0,
      "f9_score": -3,
      "f10_score": 6,
      "rankScore": 65.5,
      "rank": 2
    },
    {
      "code": "092070",
      "name": "디엔에프",
      "market": "KOSDAQ",
      "close": 22850,
      "open": 21950,
      "high": 23300,
      "low": 21450,
      "volume": 177838,
      "marketCap": 2644,
      "buyPrice": 22900,
      "target1": 26200,
      "target2": 27850,
      "stoploss": 21250,
      "rrRatio": 2.0,
      "atr": 1306,
      "riskPct": 7.2,
      "momentum": 100,
      "conditionsMet": [
        "A.200MA돌파",
        "C.전일대비상승",
        "D.양봉",
        "E.가격적정",
        "F.BB하한돌파",
        "G.거래량2.1x",
        "H.60MA상승",
        "H2.정배열(1>10>20>200)",
        "I.MACD반전",
        "J.BB반등확인",
        "K.RSI63",
        "L.시총800억+",
        "M.양봉품질",
        "N.BB중심↑106%",
        "S1.완전정배열",
        "S3.OBV매집",
        "S4.BB상단106%",
        "S5.양봉확인",
        "S6.쌍끌이매수"
      ],
      "conditionsDetail": "18/20",
      "rsi": 63.2,
      "macdHist": 286.92,
      "volumeRatio": 1.5,
      "dataDate": "2026-04-17",
      "changeRate": 4.1,
      "foreignNet5d": 4847,
      "instNet5d": 4444,
      "foreignHold": 7.5,
      "foreignBuyDays": 1,
      "instBuyDays": 2,
      "per": 213.55,
      "pbr": 1.72,
      "eps": 107.0,
      "divYield": 0.44,
      "targetPrice": 0.0,
      "recommMean": 0.0,
      "sectorRatio": 16.666666666666664,
      "high52w": 24000.0,
      "low52w": 9990.0,
      "pos52w": 92.4,
      "distFromHigh": 4.8,
      "atrRatio": 0.91,
      "squeeze": false,
      "vwapDist": 11.1,
      "cmf": 0.021,
      "rocAccel": 17.17,
      "compression": 0.86,
      "insideDays": 2,
      "z20": 2.24,
      "z60": 2.06,
      "adx": 64.6,
      "rSquared": 0.51,
      "trendSlope": 137.7,
      "advancedTotal": 15,
      "f1_score": -2,
      "f2_score": 0,
      "f3_score": 0,
      "f4_score": 2,
      "f5_score": 6,
      "f6_score": 0,
      "f7_score": 6,
      "f8_score": 0,
      "f9_score": -3,
      "f10_score": 6,
      "rankScore": 64.4,
      "rank": 3
    },
    {
      "code": "001430",
      "name": "세아베스틸지주",
      "market": "KOSPI",
      "close": 75400,
      "open": 72500,
      "high": 76100,
      "low": 70100,
      "volume": 288757,
      "marketCap": 27040,
      "buyPrice": 75600,
      "target1": 86200,
      "target2": 91500,
      "stoploss": 70300,
      "rrRatio": 2.0,
      "atr": 5300,
      "riskPct": 7.0,
      "momentum": 100,
      "conditionsMet": [
        "A.200MA돌파",
        "C.전일대비상승",
        "D.양봉",
        "E.가격적정",
        "F.BB하한돌파",
        "G.거래량1.8x",
        "H.60MA상승",
        "H2.정배열(1>10>20>200)",
        "I.MACD반전",
        "J.BB반등확인",
        "K.RSI60",
        "L.시총800억+",
        "M.양봉품질",
        "N.BB중심↑105%",
        "S1.완전정배열",
        "S3.OBV매집",
        "S4.BB상단105%",
        "S5.양봉확인",
        "S6.외인매수3일",
        "S10.업종보통"
      ],
      "conditionsDetail": "18/20",
      "rsi": 59.9,
      "macdHist": 739.99,
      "volumeRatio": 0.9,
      "dataDate": "2026-04-17",
      "changeRate": 6.95,
      "foreignNet5d": 34859,
      "instNet5d": -272829,
      "foreignHold": 7.84,
      "foreignBuyDays": 3,
      "instBuyDays": 3,
      "per": 48.12,
      "pbr": 1.39,
      "eps": 1567.0,
      "divYield": 1.59,
      "targetPrice": 86000.0,
      "recommMean": 3.9,
      "sectorRatio": 66.66666666666666,
      "high52w": 96100.0,
      "low52w": 16100.0,
      "pos52w": 78.0,
      "distFromHigh": 18.5,
      "atrRatio": 0.95,
      "squeeze": false,
      "vwapDist": 11.2,
      "cmf": 0.076,
      "rocAccel": 21.24,
      "compression": 0.86,
      "insideDays": 1,
      "z20": 2.18,
      "z60": 0.84,
      "adx": 37.6,
      "rSquared": 0.03,
      "trendSlope": 105.3,
      "advancedTotal": 13,
      "f1_score": 5,
      "f2_score": 0,
      "f3_score": 0,
      "f4_score": 5,
      "f5_score": 6,
      "f6_score": 0,
      "f7_score": 0,
      "f8_score": 0,
      "f9_score": -3,
      "f10_score": 0,
      "rankScore": 51.7,
      "rank": 4
    },
    {
      "code": "005870",
      "name": "휴니드",
      "market": "KOSPI",
      "close": 9490,
      "open": 8970,
      "high": 9730,
      "low": 8910,
      "volume": 980851,
      "marketCap": 1340,
      "buyPrice": 9510,
      "target1": 10850,
      "target2": 11520,
      "stoploss": 8840,
      "rrRatio": 2.0,
      "atr": 504,
      "riskPct": 7.0,
      "momentum": 100,
      "conditionsMet": [
        "A.200MA돌파",
        "C.전일대비상승",
        "D.양봉",
        "E.가격적정",
        "F.BB하한돌파",
        "G.거래량3.3x",
        "H.60MA상승",
        "H2.정배열(1>10>20>200)",
        "I.MACD반전",
        "J.BB반등확인",
        "K.RSI60",
        "L.시총800억+",
        "M.양봉품질",
        "N.BB중심↑102%",
        "S0.W바닥",
        "S1.단기정배열",
        "S3.OBV매집",
        "S4.BB상단102%",
        "S5.양봉확인",
        "S6.외인매수2일",
        "S7.외인29%"
      ],
      "conditionsDetail": "19/20",
      "rsi": 60.2,
      "macdHist": 63.75,
      "volumeRatio": 1.6,
      "dataDate": "2026-04-17",
      "changeRate": 5.8,
      "foreignNet5d": 88686,
      "instNet5d": -311,
      "foreignHold": 28.72,
      "foreignBuyDays": 2,
      "instBuyDays": 0,
      "per": 0.0,
      "pbr": 0.76,
      "eps": -707.0,
      "divYield": 0.0,
      "targetPrice": 0.0,
      "recommMean": 0.0,
      "sectorRatio": 16.666666666666664,
      "high52w": 11690.0,
      "low52w": 7150.0,
      "pos52w": 51.5,
      "distFromHigh": 18.8,
      "atrRatio": 1.02,
      "squeeze": false,
      "vwapDist": 6.6,
      "cmf": -0.161,
      "rocAccel": 0.18,
      "compression": 0.8,
      "insideDays": 1,
      "z20": 2.09,
      "z60": 2.45,
      "adx": 45.1,
      "rSquared": 0.2,
      "trendSlope": 27.1,
      "advancedTotal": 6,
      "f1_score": 3,
      "f2_score": 0,
      "f3_score": 2,
      "f4_score": 0,
      "f5_score": 4,
      "f6_score": 0,
      "f7_score": 0,
      "f8_score": 0,
      "f9_score": -3,
      "f10_score": 0,
      "rankScore": 46.7,
      "rank": 5
    },
    {
      "code": "450080",
      "name": "에코프로머티",
      "market": "KOSPI",
      "close": 74700,
      "open": 72100,
      "high": 76000,
      "low": 70800,
      "volume": 1364781,
      "marketCap": 52707,
      "buyPrice": 74900,
      "target1": 82200,
      "target2": 89600,
      "stoploss": 70000,
      "rrRatio": 1.49,
      "atr": 4514,
      "riskPct": 6.5,
      "momentum": 100,
      "conditionsMet": [
        "A.200MA돌파",
        "C.전일대비상승",
        "D.양봉",
        "E.가격적정",
        "F.BB하한돌파",
        "G.거래량2.0x",
        "H.60MA상승",
        "H2.정배열(1>10>20>200)",
        "I.MACD반전",
        "J.BB반등확인",
        "K.RSI58",
        "L.시총800억+",
        "M.양봉품질",
        "N.BB중심↑78%",
        "S0.W바닥",
        "S1.완전정배열",
        "S2.Stoch65",
        "S3.OBV매집",
        "S4.BB상단78%",
        "S5.양봉확인",
        "S7.외인15%",
        "S10.업종강세83%"
      ],
      "conditionsDetail": "20/20",
      "rsi": 57.6,
      "macdHist": 13.62,
      "volumeRatio": 1.0,
      "dataDate": "2026-04-17",
      "changeRate": 4.18,
      "foreignNet5d": -887970,
      "instNet5d": -73310,
      "foreignHold": 15.46,
      "foreignBuyDays": 0,
      "instBuyDays": 1,
      "per": 228.44,
      "pbr": 4.94,
      "eps": 327.0,
      "divYield": 0.0,
      "targetPrice": 0.0,
      "recommMean": 0.0,
      "sectorRatio": 83.33333333333334,
      "high52w": 78900.0,
      "low52w": 40600.0,
      "pos52w": 89.0,
      "distFromHigh": 5.3,
      "atrRatio": 0.89,
      "squeeze": false,
      "vwapDist": 4.0,
      "cmf": -0.153,
      "rocAccel": 8.78,
      "compression": 0.55,
      "insideDays": 2,
      "z20": 1.12,
      "z60": 1.6,
      "adx": 25.1,
      "rSquared": 0.28,
      "trendSlope": 303.5,
      "advancedTotal": 15,
      "f1_score": -2,
      "f2_score": 4,
      "f3_score": 2,
      "f4_score": 0,
      "f5_score": 6,
      "f6_score": 4,
      "f7_score": 0,
      "f8_score": 0,
      "f9_score": 1,
      "f10_score": 0,
      "rankScore": 28.4,
      "rank": 6
    }
  ],
  "date": "2026-04-17",
  "timestamp": "2026-04-17 12:58:41",
  "mode": "KRX+Naver",
  "count": 6,
  "dayOfWeek": "금",
  "isTuesday": false,
  "tradeRules": {
    "slip": "0.3%",
    "t1SellRatio": "1/2",
    "t2SellRatio": "1/2",
    "trailingATR": 1.5,
    "maxHold": 20,
    "skipTuesday": true,
    "skip3Loss": true
  }
}